Workbook

Sheet COBRANZA TOTAL
C2: HEG DISEÑO E INSTALACION SA DE CV
C3: TABLA DE COBRANZA A CLIENTES
C4: 13 DE OCTUBRE DEL 2025
C6: OBRAS EN PROCESO | K6: INDIRECTOS
B7: N° | C7: PROYECTO | D7: CONTROL | E7: IMPORTE CONTRATADO | F7: IMPORTE COBRADO | G7: IMPORTE A COBRAR | H7: FONDO DE GARANTIA | I7: LIQUIDO POR COBRAR | J7: FACTURAS POR COBRAR | K7: FACTOR | L7: ESPERADO | M7: COBRADO | N7: APLICADO | O7: COBRADO VS APLICADO
B8: 1 | C8: AEROPUERTO VALLARTA | D8: 00431 | E8: =+'AEROPUERTO VALLARTA'!D7 -> 580000 | F8: =+'AEROPUERTO VALLARTA'!D8 -> 435000 | G8: =+E8-F8 -> 145000 | H8: 0 | I8: =+G8-H8 -> 145000 | J8: 0 | K8: 0.3 | L8: =+E8*K8 -> 174000 | M8: =+F8*K8 -> 130500 | N8: 0 | O8: =+M8-N8 -> 130500
B9: 2 | C9: AMORES 619 | D9: 00576 | E9: =+'AMORES 619'!D7 -> 2726000 | F9: =+'AMORES 619'!D8 -> 1660000 | G9: =+E9-F9 -> 1066000 | H9: 0 | I9: =+G9-H9 -> 1066000 | J9: =+'AMORES 619'!G15 -> 135049.62 | K9: 0.2 | L9: =+E9*K9 -> 545200 | M9: =+F9*K9 -> 332000 | N9: =50000+20000+100000+40000+23911.6+61273.88+30000 -> 325185.48 | O9: =+M9-N9 -> 6814.52
B10: 3 | C10: BAHLAY 2024 | D10: 00442 | E10: =+'BAHLAY 2024'!D7 -> 28580462 | F10: =+'BAHLAY 2024'!D8 -> 24394831 | G10: =+E10-F10 -> 4185630.8 | H10: 0 | I10: =+G10-H10 -> 4185630.8 | J10: =+'BAHLAY 2024'!G15 -> 0 | K10: 0.3 | L10: =+E10*K10 -> 8574138.5 | M10: =+F10*K10 -> 7318449.3 | N10: =2500000+250000+1000000+800478+100000+951087.87+50000+20000+200000+500000+221786.93+500000+200000 -> 7293352.8 | O10: =+M10-N10 -> 25096.515
B11: 4 | C11: BAHLAY LAMINADOS HELFON | D11: 00605 | E11: =+'BAHLAY LAMINADOS H'!D7 -> 184897.14 | F11: =+'BAHLAY LAMINADOS H'!D8 -> 92449.58 | G11: =+E11-F11 -> 92447.564 | H11: 0 | I11: =+G11-H11 -> 92447.564 | J11: 0 | K11: 0.2 | L11: =+E11*K11 -> 36979.429 | M11: =+F11*K11 -> 18489.916 | N11: 0 | O11: =+M11-N11 -> 18489.916
B12: 5 | C12: BEITI | D12: 00399 | E12: =+BEITI!D7 -> 19122789 | F12: =+BEITI!D8 -> 16634790 | G12: =+E12-F12 -> 2487999.1 | H12: =+BEITI!D10 -> 573683.68 | I12: =+G12-H12 -> 1914315.4 | J12: =+BEITI!G16 -> 193568.06 | K12: 0.2 | L12: =+E12*K12 -> 3824557.9 | M12: =+F12*K12 -> 3326958.1 | N12: =2000000+200000+200000+100000+350000+593340.99+250000+20000+100000 -> 3813341 | O12: =+M12-N12 -> -486382.91
B13: 6 | C13: CASA BOSQUE DE OLMOS | D13: 00575 | E13: =+'C BOSQUE DE OLMOS'!D7 -> 2378000 | F13: =+'C BOSQUE DE OLMOS'!D8 -> 1664600 | G13: =+E13-F13 -> 713400 | H13: 0 | I13: =+G13-H13 -> 713400 | J13: =+BEITI!H18 -> 0 | K13: 0.2 | L13: =+E13*K13 -> 475600 | M13: =+F13*K13 -> 332920 | N13: =25147.35+86656.2+50000+100000+70000 -> 331803.55 | O13: =+M13-N13 -> 1116.45
B14: 7 | C14: CASA DIAZ | D14: 00579 | E14: =+'CASA DIAZ'!D7 -> 661711.19 | F14: =+'CASA DIAZ'!D8 -> 583667.61 | G14: =+E14-F14 -> 78043.579 | H14: 0 | I14: =+G14-H14 -> 78043.579 | J14: =+'CASA DIAZ'!G15 -> 0 | K14: 0.2 | L14: =+E14*K14 -> 132342.24 | M14: =+F14*K14 -> 116733.52 | N14: =50000+30313+18046.6 -> 98359.6 | O14: =+M14-N14 -> 18373.922
B15: 8 | C15: COMISIONES TECNOVIDRIO DISTR. MOSO | D15: 00614 | E15: =+'COM TECNO DISTRIB MOSO'!D7 -> 1160000 | F15: =+'COM TECNO DISTRIB MOSO'!D8 -> 1160000 | H15: 0 | I15: =+G15-H15 -> 0 | J15: =+'CASA DIAZ'!G16 -> 0
B16: 9 | C16: COMISIONES TECNOVIDRIO | E16: =+'COM TECNO'!D7 -> 3215482.2 | F16: 0 | G16: =+E16-F16 -> 3215482.2 | H16: 0 | I16: =+G16-H16 -> 3215482.2 | J16: =+'CASA DIAZ'!G17 -> 0
B17: 10 | C17: CONSTITUYENTES 7 | D17: 00607 | E17: =+'CONSTITUYENTES 7'!D7 -> 1857290.5 | F17: =+'CONSTITUYENTES 7'!D8 -> 500000 | G17: =+E17-F17 -> 1357290.5 | H17: 0 | I17: =+G17-H17 -> 1357290.5 | J17: =+'CONSTITUYENTES 7'!G15 -> 334083.85 | K17: 0.2 | L17: =+E17*K17 -> 371458.09 | M17: =+F17*K17 -> 100000 | N17: 100000 | O17: =+M17-N17 -> 0
B18: 11 | C18: COSTAVENTURA GYM Y HERRAJES INOX | D18: 00558 | E18: =+'CV GYM'!D7 -> 1475327.4 | F18: =+'CV GYM'!D8 -> 1127328.1 | G18: =+E18-F18 -> 347999.23 | H18: 0 | I18: =+G18-H18 -> 347999.23 | J18: =+'CV GYM'!G15 -> 0 | K18: 0.3 | L18: =+E18*K18 -> 442598.21 | M18: =+F18*K18 -> 338198.44 | N18: 90000 | O18: =+M18-N18 -> 248198.44
B19: 12 | C19: DECK POLANCO | D19: 00428 | E19: =+'DECK POLANCO'!D7 -> 577461.22 | F19: =+'DECK POLANCO'!D8 -> 313200 | G19: =+E19-F19 -> 264261.22 | H19: 0 | I19: =+G19-H19 -> 264261.22 | J19: =+BEITI!H21 -> 0 | K19: 0.2 | L19: =+E19*K19 -> 115492.24 | M19: =+F19*K19 -> 62640 | N19: 0 | O19: =+M19-N19 -> 62640
B20: 13 | C20: EMPORIO ACAPULCO | D20: 00448 | E20: =+'EMPORIO ACAPULCO'!D7 -> 4921927 | F20: =+'EMPORIO ACAPULCO'!D8 -> 4228155.8 | G20: =+E20-F20 -> 693771.22 | H20: =+'EMPORIO ACAPULCO'!D10 -> 492192.7 | I20: =+G20-H20 -> 201578.52 | J20: =+'EMPORIO ACAPULCO'!G15 -> 0 | K20: 0.2 | L20: =+E20*K20 -> 984385.41 | M20: =+F20*K20 -> 845631.16 | N20: 400000 | O20: =+M20-N20 -> 445631.16
B21: 14 | C21: EMPORIO ACAPULCO TORRE RANCHO | D21: 00606 | E21: =+'EMPORIO CANC TORRE R'!D7 -> 53511407 | F21: =+'EMPORIO CANC TORRE R'!D8 -> 20106844 | G21: =+E21-F21 -> 33404563 | H21: =+'EMPORIO CANC TORRE R'!D10 -> 5351140.7 | I21: =+G21-H21 -> 28053422 | J21: =+'EMPORIO CANC TORRE R'!G15 -> 0 | K21: 0.15 | L21: =+E21*K21 -> 8026711 | M21: =+F21*K21 -> 3016026.6 | N21: 152118.43 | O21: =+M21-N21 -> 2863908.2
B22: 15 | C22: FAIRMONT ACAPULCO | D22: 00556 | E22: =+'FAIRMONT ACAPULCO'!D7 -> 28284302 | F22: =+'FAIRMONT ACAPULCO'!D8 -> 27727154 | G22: =+E22-F22 -> 557148.62 | H22: =+'FAIRMONT ACAPULCO'!D10 -> 557148.61 | I22: =+G22-H22 -> 0.0071999984 | J22: =+BEITI!H25 -> 0 | K22: 0.2 | L22: =+E22*K22 -> 5656860.4 | M22: =+F22*K22 -> 5545430.7 | N22: =150000+959356.8+500000+1500000+25157.6+20000+50000+50000+250000 -> 3504514.4 | O22: =+M22-N22 -> 2040916.3
B23: 16 | C23: FLOW | D23: 00189 | E23: =+FLOW!D7 -> 53631570 | F23: =+FLOW!D8 -> 50285616 | G23: =+E23-F23 -> 3345954.4 | H23: 0 | I23: =+G23-H23 -> 3345954.4 | J23: =+BEITI!H26 -> 0 | K23: 0.15 | L23: =+E23*K23 -> 8044735.6 | M23: =+F23*K23 -> 7542842.4 | N23: 0 | O23: =+M23-N23 -> 7542842.4
B24: 17 | C24: FLOW 2025 | D24: 00592 | E24: =+'FLOW 2025'!D7 -> 818274.32 | F24: =+'FLOW 2025'!D8 -> 505734.39 | G24: =+E24-F24 -> 312539.93 | H24: 0 | I24: =+G24-H24 -> 312539.93 | J24: =+'FLOW 2025'!G15 -> 0 | K24: 0.2 | L24: =+E24*K24 -> 163654.86 | M24: =+F24*K24 -> 101146.88 | N24: =50000+8289+40000 -> 98289 | O24: =+M24-N24 -> 2857.878
B25: 18 | C25: GRAND HYATT CANCUN | D25: 00266 | E25: =+GHC!D7 -> 1.4669845e+08 | F25: =+GHC!D8 -> 91299999 | G25: =+E25-F25 -> 55398446 | H25: =+GHC!D10 -> 14669845 | I25: =+G25-H25 -> 40728602 | J25: =+GHC!G15 -> 0 | K25: 0.2 | L25: =+E25*K25 -> 29339689 | M25: =+F25*K25 -> 18260000 | N25: =228922.77*20+105500*20+110000*20 -> 8888455.4 | O25: =+M25-N25 -> 9371544.5
B26: 19 | C26: GRAND HYATT CANCUN MOSO | D26: 00623 | E26: =+' GHC MOSO'!D7 -> 8026722 | F26: =+' GHC MOSO'!D8 -> 0 | G26: =+E26-F26 -> 8026722 | I26: =+G26-H26 -> 8026722 | J26: =+' GHC MOSO'!G15 -> 5618705.4 | K26: 0.2 | L26: =+E26*K26 -> 1605344.4 | M26: =+F26*K26 -> 0 | N26: =228922.77*20+105500*20+110000*20 -> 8888455.4 | O26: =+M26-N26 -> -8888455.4
B27: 20 | C27: HOTEL COPACABANA | D27: 00449 | E27: =+'HOTEL COPACABANA'!D7 -> 28840306 | F27: =+'HOTEL COPACABANA'!D8 -> 25293839 | G27: =+E27-F27 -> 3546467.1 | H27: =+'HOTEL COPACABANA'!D10 -> 2884030.6 | I27: =+G27-H27 -> 662436.45 | J27: =+'HOTEL COPACABANA'!G15 -> 500000.01 | K27: 0.15 | L27: =+E27*K27 -> 4326045.9 | M27: =+F27*K27 -> 3794075.8 | N27: =160000+100000 -> 260000 | O27: =+M27-N27 -> 3534075.8
B28: 21 | C28: JAIME NUNO | D28: 00443 | E28: =+'JAIME NUNO'!D7 -> 61450000 | F28: =+'JAIME NUNO'!D8 -> 51982458 | G28: =+E28-F28 -> 9467542.5 | H28: 0 | I28: =+G28-H28 -> 9467542.5 | J28: =+'JAIME NUNO'!G15 -> 0 | K28: 0.2 | L28: =+E28*K28 -> 12290000 | M28: =+F28*K28 -> 10396492 | N28: =1500000+1160000+200000 -> 2860000 | O28: =+M28-N28 -> 7536491.5
B29: 22 | C29: LA MEXICANA / LB600 (CASETA) | D29: 00323 | E29: 588816 | F29: 471032.56 | G29: =+E29-F29 -> 117783.44 | H29: 0 | I29: =+G29-H29 -> 117783.44 | J29: =+PARALLEL!G25 -> 0 | K29: 0.2 | L29: =+E29*K29 -> 117763.2 | M29: =+F29*K29 -> 94206.512 | N29: 0 | O29: =+M29-N29 -> 94206.512
B30: 23 | C30: LANDMARK GUADALAJARA CON VIATICOS | D30: 00363/00415/ 00416 | E30: 1.33e+08 | F30: 1.2965276e+08 | G30: =+E30-F30 -> 3347235.8 | H30: =+'LANDMARK GDL RESIDENCIAL'!D10+'LANDMARK COMERCIO'!D10 -> 3356401.4 | I30: =+G30-H30 -> -9165.6451 | J30: =+'LANDMARK COMERCIO'!G16 -> 0 | K30: 0.1 | L30: =+E30*K30 -> 13300000 | M30: =+F30*K30 -> 12965276 | N30: =400000+500000+1848702.69+150000+700000+430000+500000+400000+250000+1686490.91+1000000+450000+200000+500000+1000000+1000000+20000+100000+175526.35+100000+400000 -> 11810720 | O30: =+M30-Q28 -> 12965276
B31: 24 | C31: LANDMARK TIJUANA | D31: 00439/00446/'00571 | E31: 49736609 | F31: 40463666 | G31: =+E31-F31 -> 9272943 | H31: =+'LANDMARK TIJUANA RES'!D10+'LANDMARK TIJUANA INTERIORES'!D10 -> 2147162 | I31: =+G31-H31 -> 7125781 | J31: 4345581.7 | K31: 0.2 | L31: =+E31*K31 -> 9947321.8 | M31: =+F31*K31 -> 8092733.2 | N31: =200000+500000 -> 700000 | O31: =+M31-N31 -> 7392733.2
B32: 25 | C32: MARIANO ESCOBEDO | D32: 00560 | E32: =+'MARIANO ESCOBEDO'!D7 -> 38824118 | F32: =+'MARIANO ESCOBEDO'!D8 -> 32373000 | G32: =+E32-F32 -> 6451118.1 | H32: 0 | I32: =+G32-H32 -> 6451118.1 | J32: 0 | K32: 0.2 | L32: =+E32*K32 -> 7764823.6 | M32: =+F32*K32 -> 6474600 | N32: =1500000+400000+500000 -> 2400000 | O32: =+M32-N32 -> 4074600
B33: 26 | C33: MAURICIO CAPON | D33: 00593 | E33: =+'MAURICIO CAPON'!D7 -> 3737883.4 | F33: =+'MAURICIO CAPON'!D8 -> 1868941.1 | G33: =+E33-F33 -> 1868942.3 | H33: 0 | I33: =+G33-H33 -> 1868942.3 | J33: 0 | K33: 0.2 | L33: =+E33*K33 -> 747576.69 | M33: =+F33*K33 -> 373788.22 | N33: =100000+100000+100000+17597.19 -> 317597.19 | O33: =+M33-N33 -> 56191.028
B34: 27 | C34: MITIKAH | D34: 00316 | E34: =62149276.95*1.16 -> 72093161 | F34: =57294036.65*1.16 -> 66461083 | G34: =+E34-F34-1379414.19 -> 4252664.6 | H34: =3666090.14*1.16 -> 4252664.6 | I34: =+G34-H34 -> -0.0043999963 | K34: 0.1
B35: 28 | C35: MONTE AZUL 2024 | D35: 00561 | E35: =+'MONTE AZUL 2024'!D7 -> 2185946.2 | F35: =+'MONTE AZUL 2024'!D8 -> 1160000 | G35: =+E35-F35 -> 1025946.2 | H35: 0 | I35: =+G35-H35 -> 1025946.2 | J35: 0 | K35: 0.2 | L35: =+E35*K35 -> 437189.23 | M35: =+F35*K35 -> 232000 | N35: =100000+150000 -> 250000 | O35: =+M35-N35 -> -18000
B36: 29 | C36: MONTES URALES | D36: 00015 | E36: =+MU!D7 -> 20772762 | F36: =+MU!D8 -> 16914241 | G36: =+E36-F36 -> 3858520.6 | H36: =+MU!D10 -> 0 | I36: =+G36-H36 -> 3858520.6 | J36: =+MU!G15 -> 0 | K36: 0.25 | L36: =+E36*K36 -> 5193190.4 | M36: =+F36*K36 -> 4228560.3 | N36: =242405.33+511905.1+200000+477251.57+285000+800000+200000+90000+400000+300000+50000+35935.04 -> 3592497 | O36: =+M36-N36 -> 636063.22
B37: 30 | C37: MONTES URALES 2025 | D37: 00602 | E37: =+'MU 2025'!D7 -> 284540.1 | F37: =+'MU 2025'!D8 -> 242013.01 | G37: =+E37-F37 -> 42527.09 | H37: 0 | I37: =+G37-H37 -> 42527.09 | J37: =+'MU 2025'!G15 -> 0 | K37: 0.2 | L37: =+E37*K37 -> 56908.02 | M37: =+F37*K37 -> 48402.602 | N37: 0 | O37: =+M37-N37 -> 48402.602
B38: 31 | C38: NAARA | D38: 00426 | E38: =+NAARA!D7 -> 31198824 | F38: =+NAARA!D8 -> 30357849 | G38: =+E38-F38 -> 840975.81 | H38: =+NAARA!D10 -> 393315.86 | I38: =+G38-H38 -> 447659.95 | J38: 0 | K38: 0.2 | L38: =+E38*K38 -> 6239764.9 | M38: =+F38*K38 -> 6071569.7 | N38: =150000+500000+900000+200000+46809.2+200000+500000+400000+500000+1000000+904961.13+50000+10000+700000 -> 6061770.3 | O38: =+M38-N38 -> 9799.388
B39: 32 | C39: NAARA PISO 2 | D39: 00624 | E39: =209941.82*1.16 -> 243532.51 | F39: 170472.59 | G39: =+E39-F39 -> 73059.921 | H39: 0 | I39: =+G39-H39 -> 73059.921 | J39: 0
B40: 33 | C40: NAARA PISO 7 | D40: 00578 | E40: 222099.79 | F40: 155469.86 | G40: =+E40-F40 -> 66629.93 | H40: 0 | I40: =+G40-H40 -> 66629.93 | J40: 0 | K40: 0.2 | L40: =+E40*K40 -> 44419.958 | M40: =+F40*K40 -> 31093.972 | N40: 30000 | O40: =+M40-N40 -> 1093.972
B41: 34 | C41: NAARA PISO 9 | D41: 00588 | E41: 222099.79 | F41: 155469.86 | G41: =+E41-F41 -> 66629.934 | H41: 0 | I41: =+G41-H41 -> 66629.934 | J41: =+PARALLEL!G27 -> 0 | K41: 0.2 | L41: =+E41*K41 -> 44419.959 | M41: =+F41*K41 -> 31093.972 | N41: =20000+50000 -> 70000 | O41: =+M41-N41 -> -38906.028
B42: 35 | C42: NUA INTERLOMAS (FASE I, II, III, IV, V) | D42: 555 | E42: =+'NUA INTERLOMAS'!D7 -> 81729902 | F42: =+'NUA INTERLOMAS'!D8 -> 74390373 | G42: =+E42-F42 -> 7339529.8 | H42: =+'NUA INTERLOMAS'!D10 -> 0 | I42: =+G42-H42 -> 7339529.8 | J42: =+'NUA INTERLOMAS'!G15 -> 0 | K42: 0.2 | L42: =+E42*K42 -> 16345980 | M42: =+F42*K42 -> 14878075 | N42: =1993212.5+1136307+200000+2000000+500000+652591.29+150000+600000+100000+500000+189235.15+1500000+400000+600000+500000*6+1000000+500000+280000+100000 -> 15401346 | O42: =+M42-N42 -> -523271.4
B43: 36 | C43: OCEAN CLUB INSTALACION | D43: ´00554 | E43: =+'OCEAN CLUB INST'!D7 -> 11483545 | F43: =+'OCEAN CLUB INST'!D8 -> 9489984.2 | G43: =+E43-F43 -> 1993560.7 | H43: 0 | I43: =+G43-H43 -> 1993560.7 | J43: =+'OCEAN CLUB INST'!G15 -> 480000 | K43: 0.2 | L43: =+E43*K43 -> 2296709 | M43: =+F43*K43 -> 1897996.8 | N43: =904961.13+500000 -> 1404961.1 | O43: =+M43-N43 -> 493035.72
B44: 37 | C44: OCEAN CLUB MATERIALES | D44: 00550 | E44: =+'OCEAN CLUB MAT'!D7 -> 17197639 | F44: =+'OCEAN CLUB MAT'!D8 -> 17197636 | G44: =+E44-F44 -> 2.8256 | H44: 0 | I44: =+G44-H44 -> 2.8256 | J44: =+'OCEAN CLUB MAT'!G15 -> 0 | K44: 0.2 | L44: =+E44*K44 -> 3439527.8 | M44: =+F44*K44 -> 3439527.2 | N44: =1500000 -> 1500000 | O44: =+M44-N44 -> 1939527.2
B45: 38 | C45: PARALLEL | D45: 00182 | E45: =+PARALLEL!D7 -> 44512359 | F45: =+E45 -> 44512359 | G45: =+E45-F45 -> 0 | H45: 0 | I45: =+G45-H45 -> 0 | J45: =+PARALLEL!G15 -> 0 | K45: 0.1 | L45: =+E45*K45 -> 4451235.9 | M45: =+F45*K45 -> 4451235.9 | N45: =441985.06+1000000+89547.45 -> 1531532.5 | O45: =+M45-N45 -> 2919703.4
B46: 39 | C46: PARALLEL 2025 | D46: 00589 | E46: =+'PARALLEL 2025'!D7 -> 794951.41 | F46: =+'PARALLEL 2025'!D8 -> 464351.41 | G46: =+E46-F46 -> 330600 | H46: 0 | I46: =+G46-H46 -> 330600 | J46: =+'PARALLEL 2025'!G15 -> 0 | K46: 0.2 | L46: =+E46*K46 -> 158990.28 | M46: =+F46*K46 -> 92870.282 | N46: 0 | O46: =+M46-N46 -> 92870.282
B47: 40 | C47: PARALLEL HOP | D47: 00580 | E47: =+'PARALLEL HOP'!D7 -> 317799.33 | F47: =+'PARALLEL HOP'!D8 -> 188090.13 | G47: =+E47-F47 -> 129709.2 | H47: 0 | I47: =+G47-H47 -> 129709.2 | J47: 0 | K47: 0.2 | L47: =+E47*K47 -> 63559.866 | M47: =+F47*K47 -> 37618.026 | N47: 0 | O47: =+M47-N47 -> 37618.026
B48: 41 | C48: POPOCATEPETL 2025 | D48: 00618 | E48: 330000 | F48: 231000 | G48: =+E48-F48 -> 99000 | H48: 0 | I48: =+G48-H48 -> 99000 | J48: =330000-231000 -> 99000 | K48: 0.2 | L48: =+E48*K48 -> 66000 | M48: =+F48*K48 -> 46200 | N48: 0 | O48: =+M48-N48 -> 46200
B49: 42 | C49: PUERTA POLANCO 2025 | D49: 00590 | E49: =+'PUERTA POLANCO'!D7 -> 198456.23 | F49: =+'PUERTA POLANCO'!D8 -> 145131.7 | G49: =+E49-F49 -> 53324.534 | H49: 0 | I49: =+G49-H49 -> 53324.534 | J49: =+'PUERTA POLANCO'!G15 -> 0 | K49: 0.1 | L49: =+E49*K49 -> 19845.623 | M49: =+F49*K49 -> 14513.17 | N49: 0 | O49: =+M49-N49 -> 14513.17
B50: 43 | C50: REFORMA 445 | D50: 00567 | E50: =+'REFORMA 445'!D7 -> 133604000 | F50: =+'REFORMA 445'!D8 -> 94590000 | G50: =+E50-F50 -> 39014000 | H50: 0 | I50: =+G50-H50 -> 39014000 | J50: =+'REFORMA 445'!G15 -> 0 | K50: 0.2 | L50: =+E50*K50 -> 26720800 | M50: =+F50*K50 -> 18918000 | N50: =1512443+2436+66700+14189.13+112220.2+481201.16+353841.99+328283.48+904961.13+565205.06+353194.62+137808.94 -> 4832484.7 | O50: =+M50-N50 -> 14085515
B51: 44 | C51: ST REGIS PINTURA | D51: 00619 | E51: =+F51 -> 798000 | F51: =348000+300000+150000 -> 798000 | G51: 0 | H51: 0 | I51: 0 | K51: 0 | L51: =+E51*K51 -> 0 | M51: =+F51*L51 -> 0 | N51: =+G51*M51 -> 0 | O51: =+H51*N51 -> 0
B52: 45 | C52: TAXCO CUERNAVACA | D52: 00564 | E52: =+'TAXCO CUERNAVACA'!D7 -> 763066.39 | F52: =+'TAXCO CUERNAVACA'!D8 -> 400000 | G52: =+E52-F52 -> 363066.39 | H52: 0 | I52: =+G52-H52 -> 363066.39 | J52: 0 | K52: 0.2 | L52: =+E52*K52 -> 152613.28 | M52: =+F52*K52 -> 80000 | N52: 0 | O52: =+M52-N52 -> 80000
B53: 46 | C53: TORRE BOSQUES | D53: 00620 | E53: =+'TORRE BOSQUES'!D7 -> 268606.26 | F53: =+'TORRE BOSQUES'!D8 -> 188024.38 | G53: =+E53-F53 -> 80581.879 | H53: 0 | I53: =+G53-H53 -> 80581.879 | J53: 0 | K53: 0.2 | L53: =+E53*K53 -> 53721.252 | M53: =+F53*K53 -> 37604.876 | N53: 0 | O53: =+M53-N53 -> 37604.876
B54: 47 | C54: TORRE VIRREYES AUDITORIO | D54: 00563 | E54: ='T VIRREYES AUDITORIO'!D7 -> 3384631.8 | F54: ='T VIRREYES AUDITORIO'!D8 -> 3384631.8 | G54: =+E54-F54 -> 0.046399999 | H54: =+'T VIRREYES AUDITORIO'!D10 -> 338463.18 | I54: =+G54-H54 -> -338463.13 | J54: =+'T VIRREYES AUDITORIO'!G15 -> 0 | K54: 0.2 | L54: =+E54*K54 -> 676926.36 | M54: =+F54*K54 -> 676926.35 | N54: =373776.25+50000+100000 -> 523776.25 | O54: =+M54-N54 -> 153150.1
B55: 48 | C55: VIDALTA 2803 (ALTAIRE) | D55: 00573 | E55: =+'VIDALTA 2803'!D7 -> 470854.29 | F55: =+'VIDALTA 2803'!D8 -> 356055 | G55: =+E55-F55 -> 114799.29 | H55: 0 | I55: =+G55-H55 -> 114799.29 | J55: =+PARALLEL!G33 -> 0 | K55: 0.2 | L55: =+E55*K55 -> 94170.858 | M55: =+F55*K55 -> 71211 | N55: =50000+9928 -> 59928 | O55: =+M55-N55 -> 11283
B56: 49 | C56: VILLAS KANAI (CANCELERIA Y BAMBU) | D56: 00427 | E56: =+'VILLAS KANAI'!D7 -> 5257120 | F56: =+'VILLAS KANAI'!D8 -> 4494611.2 | G56: =+E56-F56 -> 762508.76 | H56: 0 | I56: =+G56-H56 -> 762508.76 | J56: 0 | K56: 0.2 | L56: =+E56*K56 -> 1051424 | M56: =+F56*K56 -> 898922.25 | N56: =250000+200000+200000 -> 650000 | O56: =+M56-N56 -> 248922.25
B57: 50 | C57: VILLAS KANAI 2025 | D57: 00581 | E57: =+'VILLAS KANAI 2025'!D7 -> 1552384.5 | F57: =+'VILLAS KANAI 2025'!D8 -> 1426689.9 | G57: =+E57-F57 -> 125694.65 | H57: 0 | I57: =+G57-H57 -> 125694.65 | J57: =+'VILLAS KANAI 2025'!G14 -> 0 | K57: 0.2 | L57: =+E57*K57 -> 310476.91 | M57: =+F57*K57 -> 285337.98 | N57: 100000 | O57: =+M57-N57 -> 185337.98
B58: 51 | C58: VOLCAN 150 2024 | D58: 00568 | E58: =+'VOLCAN 150'!D7 -> 116534.32 | F58: =+'VOLCAN 150'!F41 -> 0 | G58: =+E58-F58 -> 116534.32 | H58: 0 | I58: =+G58-H58 -> 116534.32 | J58: =+'VOLCAN 150'!G14 -> 0 | K58: 0.2 | L58: =+E58*K58 -> 23306.864 | M58: =+F58*K58 -> 0 | N58: 0 | O58: =+M58-N58 -> 0
B59: 52 | C59: WESTIN GUADALAJARA | D59: 00594 | E59: =+'WESTIN GDL '!D7 -> 435812 | F59: =+'WESTIN GDL '!D8 -> 305068.4 | G59: =+E59-F59 -> 130743.6 | H59: 0 | I59: =+G59-H59 -> 130743.6 | J59: =+'WESTIN GDL '!G14 -> 130743.6 | K59: 0.2 | L59: =+E59*K59 -> 87162.4 | M59: =+F59*K59 -> 61013.68 | N59: =37263.19+20000 -> 57263.19 | O59: =+M59-N59 -> 3750.49
C60: TOTAL | E60: =SUM(E10:E59) -> 1.1017224e+09 | F60: =SUM(F10:F59) -> 8.9090867e+08 | G60: =SUM(G10:G59) -> 2.0943434e+08 | H60: =SUM(H10:H59) -> 35016048 | I60: =SUM(I10:I59) -> 1.7441829e+08 | J60: =SUM(J8:J59) -> 11836732 | L60: =SUM(L10:L59) -> 1.8431642e+08 | M60: =SUM(M10:M59) -> 1.4564641e+08 | N60: =SUM(N10:N59) -> 88072566 | O60: =SUM(O10:O59) -> 69384565
I61: =+I60+H60 -> 2.0943434e+08
C64: OBRAS PENDIENTES DE COBRO:
B65: N° | C65: PROYECTO | D65: CONTROL | E65: IMPORTE CONTRATADO | F65: IMPORTE COBRADO | G65: IMPORTE A COBRAR | H65: FONDO DE GARANTIA | I65: LIQUIDO POR COBRAR | J65: FACTURAS POR COBRAR | K65: FACTOR | L65: ESPERADO | M65: COBRADO | N65: APLICADO | O65: COBRADO VS APLICADO
B66: 1 | C66: BANBAJIO | D66: 00445 | E66: =+BANBAJIO!D7 -> 696000 | F66: 522000 | G66: =+E66-F66 -> 174000 | H66: 0 | I66: =+G66-H66 -> 174000 | J66: =+BANBAJIO!G15 -> 0 | K66: 0.3 | L66: =+E66*K66 -> 208800 | M66: =+F66*K66 -> 156600 | N66: =50000+50000 -> 100000 | O66: =+M66-N66 -> 56600
B67: 2 | C67: CDI BEITI (BANAI)MUESTRA | D67: 399 | E67: =+'BEITI MUESTRA'!D7 -> 130408.4 | F67: =+'BEITI MUESTRA'!D8 -> 91285.88 | G67: =+E67-F67 -> 39122.52 | H67: 0 | I67: =+G67-H67 -> 39122.52 | J67: =+BEITI!H17 -> 0 | K67: 0.2 | L67: =+E67*K67 -> 26081.68 | M67: =+F67*K67 -> 18257.176 | N67: 0 | O67: =+M67-N67 -> 18257.176
B68: 3 | C68: CASA HELFON LA PUNTA | D68: 00413 | E68: 53528.85 | F68: 37470.19 | G68: =+E68-F68 -> 16058.66 | H68: 0 | I68: =+G68-H68 -> 16058.66 | J68: =+PARALLEL!G30 -> 0 | K68: 0 | L68: =+E68*K68 -> 0 | M68: =+F68*K68 -> 0 | N68: 0 | O68: =+M68-N68 -> 0
B69: 4 | C69: COLIMA 426 | D69: 00418 | E69: =+'COLIMA 426'!D7 -> 426201.95 | F69: =+'COLIMA 426'!D8 -> 298341.36 | G69: =+E69-F69 -> 127860.59 | H69: 0 | I69: =+G69-H69 -> 127860.59 | J69: =+BEITI!H19 -> 0 | K69: 0.2 | L69: =+E69*K69 -> 85240.39 | M69: =+F69*K69 -> 59668.272 | N69: 0 | O69: =+M69-N69 -> 59668.272
B70: 6 | C70: EDITION X-TREME | D70: 00562 | E70: =+'EDITION KANAI X-TREME'!D7 -> 27519818 | F70: =+'EDITION KANAI X-TREME'!D8 -> 26992714 | G70: =+E70-F70 -> 527104.36 | H70: 0 | I70: =+G70-H70 -> 527104.36 | J70: =+BEITI!H23 -> 0 | K70: 0.3 | L70: =+E70*K70 -> 8255945.4 | M70: =+F70*K70 -> 8097814.1 | N70: =100000*17+200000+575000+500000+773193.43+34714.2+2059168.13+89656.2+636568.55+378169.27+33518.2+179579.22+200000+300000+200000 -> 7859567.2 | O70: =+M70-N70 -> 238246.88
B71: 7 | C71: EDITION KANAI | D71: 00225 | E71: =+'EDITION KANAI'!D7 -> 43754583 | F71: =+'EDITION KANAI'!D8 -> 41364024 | G71: =+E71-F71 -> 2390558.7 | H71: =+'EDITION KANAI'!D10 -> 2187729.2 | I71: =+G71-H71 -> 202829.58 | J71: =+BEITI!H22 -> 0 | K71: 0 | L71: =+E71*K71 -> 0 | M71: =+F71*K71 -> 0 | N71: =71369+962.26 -> 72331.26 | O71: =+M71-N71 -> -72331.26
B72: 8 | C72: EDITION LIMPIEZA MOSO (TC 17.5) | D72: 00433 | E72: 4858114.8 | F72: 4858114.8 | G72: =+E72-F72 -> 0 | H72: 0 | I72: =+G72-H72 -> 0 | J72: =+PARALLEL!G16 -> 0 | K72: 0.2 | L72: =+E72*K72 -> 971622.96 | M72: =+F72*K72 -> 971622.96 | N72: =50000+200000+100000+15533.02+100000+100000+8053.72*17.5+250000+11082.6 -> 967555.72 | O72: =+M72-N72 -> 4067.24
B73: 9 | C73: GRAND HYATT CANCUN (CUARTO MUESTRA) | D73: 00266 | E73: 764672.39 | F73: 573347.8 | G73: =+E73-F73 -> 191324.59 | H73: 0 | I73: =+G73-H73 -> 191324.59 | J73: =+PARALLEL!G19 -> 0 | K73: 0.2 | L73: =+E73*K73 -> 152934.48 | M73: =+F73*K73 -> 114669.56 | N73: 0 | O73: =+M73-N73 -> 114669.56
B74: 10 | C74: JAIME FASJA | D74: 00436 | E74: 447777.71 | F74: 348000 | G74: =+E74-F74 -> 99777.713 | H74: 0 | I74: =+G74-H74 -> 99777.713 | J74: =+PARALLEL!G20 -> 0 | K74: 0.2 | L74: =+E74*K74 -> 89555.543 | M74: =+F74*K74 -> 69600 | N74: 261864.01 | O74: =+M74-N74 -> -192264.01
B75: 11 | C75: LANDMARK GUADALAJARA MATERIALES | D75: 00363 | E75: 79950000 | F75: 79950000 | G75: =+E75-F75 -> -0.0099999905 | H75: 0 | I75: =+G75-H75 -> -0.0099999905 | J75: =+PARALLEL!G21 -> 0 | K75: 0.1325829 | L75: =+E75*K75 -> 10600003 | M75: =+F75*K75 -> 10600003 | N75: =1393226.06+1000000+1700000+1000000+600000+1127556.22+136406.82+1800000+1000000+2000000 -> 11757189 | O75: =+M75-N75 -> -1157186.2
B76: 12 | C76: LANDMARK PAGOS EN EFECTIVO | D76: S/C | E76: 10000000 | F76: 10000000 | G76: 0 | H76: 0 | I76: =+G76-H76 -> 0 | J76: =+PARALLEL!G22 -> 0 | K76: 0 | L76: =+E76*K76 -> 0 | M76: =+F76*K76 -> 0 | N76: 0 | O76: =+M76-N76 -> 0
B77: 13 | C77: LANDMARK TIJUANA MATERIALES | D77: 00439 | E77: 32699175 | F77: 32699176 | G77: -0.75 | H77: 0 | I77: =+G77-H77 -> -0.75 | J77: =+PARALLEL!G23 -> 0 | K77: 0.2 | L77: =+E77*K77 -> 6539835 | M77: =+F77*K77 -> 6539835.2 | N77: =1500000+1300000+500000+500000+500000+600000+2000000+1012745.41+250000 -> 8162745.4 | O77: =+M77-N77 -> -1622910.2
B78: 14 | C78: MIRALTA | D78: 00157 | E78: =+MIRALTA!D7 -> 82516469 | F78: =+MIRALTA!D8 -> 81186447 | G78: =+E78-F78 -> 1330022 | H78: 0 | I78: =+G78-H78 -> 1330022 | J78: 0 | K78: 0 | L78: =+E78*K78 -> 0 | M78: =+F78*K78 -> 0 | N78: =150000+146868+100000 -> 396868 | O78: =+M78-N78 -> -396868
B79: 15 | C79: MONTE AZUL | D79: 00381 | E79: 817455.28 | F79: 556000 | G79: =+E79-F79 -> 261455.28 | H79: 0 | I79: =+G79-H79 -> 261455.28 | J79: =+PARALLEL!G17 -> 0 | K79: 0.2 | L79: =+E79*K79 -> 163491.06 | M79: =+F79*K79 -> 111200 | N79: 0 | O79: =+M79-N79 -> 111200
B80: 16 | C80: OCEAN CLUB GH101 | D80: 00601 | E80: 534423.11 | F80: 534423.11 | G80: =+E80-F80 -> 0 | H80: 0 | I80: =+G80-H80 -> 0 | J80: =+PARALLEL!G24 -> 0 | K80: 0.2 | L80: =+E80*K80 -> 106884.62 | M80: =+F80*K80 -> 106884.62 | N80: =100000+57684.67 -> 157684.67 | O80: =+M80-N80 -> -50800.047
B81: 17 | C81: PARK PLAZA PUENTE PEATONAL | D81: 00324 | E81: 1218000 | F81: 883049.06 | G81: =+E81-F81 -> 334950.94 | H81: 0 | I81: =+G81-H81 -> 334950.94 | J81: =+PARALLEL!G31 -> 0 | K81: 0 | L81: =+E81*K81 -> 0 | M81: =+F81*K81 -> 0 | N81: 0 | O81: =+M81-N81 -> 0
B82: 18 | C82: ST. REGIS KANAI | D82: 00343 | E82: =+'ST REGIS '!D7 -> 86969393 | F82: =+'ST REGIS '!D8 -> 81568963 | G82: =+E82-F82 -> 5400429.3 | H82: =+'ST REGIS '!D10 -> 4348469.6 | I82: =+G82-H82 -> 1051959.7 | J82: 0 | K82: 0 | L82: =+E82*K82 -> 0 | M82: =+F82*K82 -> 0 | N82: 0 | O82: =+M82-N82 -> 0
B83: 19 | C83: TERRAZA LILY WESTIN STA FE | D83: 00424 | E83: 184662.05 | F83: 0 | G83: =+E83-F83 -> 184662.05 | H83: 0 | I83: =+G83-H83 -> 184662.05 | J83: =+PARALLEL!G32 -> 0 | K83: 0 | L83: =+E83*K83 -> 0 | M83: =+F83*K83 -> 0 | N83: 0 | O83: =+M83-N83 -> 0
B84: 20 | C84: TORRE CHAPULTEPEC | D84: 00569 | E84: =+'T CHAPULTEPEC'!D7 -> 64889.46 | F84: =+'T CHAPULTEPEC'!D8 -> 64890.46 | G84: =+E84-F84 -> -1 | H84: 0 | I84: =+G84-H84 -> -1 | J84: =+'T CHAPULTEPEC'!G15 -> 0 | K84: 0.2 | L84: =+E84*K84 -> 12977.892 | M84: =+F84*K84 -> 12978.092 | N84: 0 | O84: =+M84-N84 -> 12978.092
B85: 21 | C85: TORRE REFORMA MANTENIMIENTO | D85: 00412 | E85: =+'T REFORMA MTTO'!D7 -> 12166.54 | F85: 0 | G85: =+E85-F85 -> 12166.54 | H85: 0 | I85: =+G85-H85 -> 12166.54 | J85: =+'T REFORMA MTTO'!G15 -> 12166.54 | K85: 0.2 | L85: =+E85*K85 -> 2433.308 | M85: =+F85*K85 -> 0 | N85: =18207.4+100000 -> 118207.4 | O85: =+M85-N85 -> -118207.4
B86: 23 | C86: VILLA 103 CABO | D86: 00365 | E86: 4259779.1 | F86: 3890500.2 | G86: =+E86-F86 -> 369278.86 | H86: 0 | I86: =+G86-H86 -> 369278.86 | J86: =+PARALLEL!G28 -> 0 | K86: 0.1 | L86: =+E86*K86 -> 425977.91 | M86: =+F86*K86 -> 389050.02 | N86: 0 | O86: =+M86-N86 -> 389050.02
B87: 24 | C87: VILLA 111 CABO | D87: 00365 | E87: 911935.23 | F87: 940379.42 | G87: =+E87-F87 -> -28444.19 | H87: 0 | I87: =+G87-H87 -> -28444.19 | J87: =+PARALLEL!G29 -> 0 | K87: 0.1 | L87: =+E87*K87 -> 91193.523 | M87: =+F87*K87 -> 94037.942 | N87: =30000+123409.63 -> 153409.63 | O87: =+M87-N87 -> -59371.688
B88: 25 | C88: WESTIN SANTA FE SPA | D88: 00269 | E88: 118759.66 | F88: 81200 | G88: =+E88-F88 -> 37559.663 | H88: 0 | I88: =+G88-H88 -> 37559.663 | J88: =+PARALLEL!G34 -> 0 | K88: 0 | L88: =+E88*K88 -> 0 | M88: =+F88*K88 -> 0 | N88: 0 | O88: =+M88-N88 -> 0
B89: 26 | C89: VIDALTA TORRE LUX | D89: 00068 | E89: =+VTLUX!D7 -> 1.3011247e+08 | F89: =+VTLUX!D8 -> 1.2970971e+08 | G89: =+E89-F89 -> 402753.62 | H89: 0 | I89: =+G89-H89 -> 402753.62 | J89: 0 | K89: 0 | L89: =+E89*K89 -> 0 | M89: =+F89*K89 -> 0 | N89: 0 | O89: =+M89-N89 -> 0
C90: TOTAL | E90: =SUM(E67:E89) -> 5.0832468e+08 | F90: =SUM(F67:F89) -> 4.9662804e+08 | G90: =SUM(G67:G89) -> 11696640 | H90: =SUM(H67:H89) -> 6536198.8 | I90: =SUM(I67:I89) -> 5160440.7 | J90: =SUM(J18:J89) -> 23022929 | L90: =SUM(L8:L89) -> 3.9708502e+08 | M90: =SUM(M8:M89) -> 3.1909754e+08 | N90: =SUM(N8:N89) -> 2.0647774e+08 | O90: =SUM(O8:O89) -> 1.3624124e+08
I91: =+I90+H90 -> 11696640

Sheet AEROPUERTO VALLARTA
A2: COMPAÑÍA: | B2: HEG DISEÑO E INSTALACION SA DE CV
A3: CONCEPTO: | B3: FACTURAS PENDIENTES DE COBRO DEL PROYECTO AEROPUERTO VALLARTA
A4: FECHA: | B4: 02 DE AGOSTO DEL 2024
B6: CONCEPTO | D6: IMPORTE
B7: CONTRATADO A LA FECHA | D7: =250000*2*1.16 -> 580000
B8: COBRADO | D8: =290000+145000 -> 435000
B9: POR COBRAR | D9: =+D7-D8 -> 145000
B10: FONDO DE GARANTIA | D10: 0
B11: LQUIDO POR COBRAR | D11: =+D9-D10 -> 145000
A13: N° | B13: FECHA | C13: N° FACTURA | D13: CONCEPTO | E13: IMPORTE A COBRAR | F13: IMPORTE COBRADO | G13: SALDO POR COBRAR | H13: FECHA DE PAGO

Sheet AMORES 619
A2: COMPAÑÍA: | B2: HEG DISEÑO E INSTALACION SA DE CV
A3: CONCEPTO: | B3: FACTURAS PENDIENTES DE COBRO DEL PROYECTO AMORES
A4: FECHA: | B4: 07 DE OCTUBRE DEL 2025
B6: CONCEPTO | D6: IMPORTE
B7: CONTRATADO A LA FECHA | D7: 2726000
B8: COBRADO | D8: 1660000
B9: POR COBRAR | D9: =+D7-D8 -> 1066000
B10: FONDO DE GARANTIA | D10: 0
B11: LQUIDO POR COBRAR | D11: =+D9-D10 -> 1066000
A13: N° | B13: FECHA | C13: N° FACTURA | D13: CONCEPTO | E13: IMPORTE A COBRAR | F13: IMPORTE COBRADO | G13: SALDO POR COBRAR | H13: FECHA DE PAGO
A14: 1 | B14: 45931 | C14: 4318 | D14: EST 01 | E14: 135049.62 | F14: 0 | G14: 135049.62
E15: =SUM(E14) -> 135049.62 | F15: =SUM(F14) -> 0 | G15: =SUM(G14) -> 135049.62

Sheet BAHLAY 2024
A2: COMPAÑÍA: | B2: HEG DISEÑO E INSTALACION SA DE CV
A3: CONCEPTO: | B3: FACTURAS PENDIENTES DE COBRO DEL PROYECTO BAHLAY 2024
A4: FECHA: | B4: 23 DE SEPTIEMBRE DEL 2025
B6: CONCEPTO | D6: IMPORTE
B7: CONTRATADO A LA FECHA | D7: 28580462
B8: COBRADO | D8: =23185015.9195499+822504.69+252964.68+134345.76 -> 24394831
B9: POR COBRAR | D9: =+D7-D8 -> 4185630.8
B10: FONDO DE GARANTIA | D10: 0
B11: LQUIDO POR COBRAR | D11: =+D9-D10 -> 4185630.8
A13: N° | B13: FECHA | C13: N° FACTURA | D13: CONCEPTO | E13: IMPORTE A COBRAR | F13: IMPORTE COBRADO | G13: SALDO POR COBRAR | H13: FECHA DE PAGO
E15: 0 | F15: 0 | G15: 0

Sheet BAHLAY LAMINADOS H
A2: COMPAÑÍA: | B2: HEG DISEÑO E INSTALACION SA DE CV
A3: CONCEPTO: | B3: FACTURAS PENDIENTES DE COBRO DEL PROYECTO BAHLAY LAMINADOS HELFON
A4: FECHA: | B4: 13 DE JUNIO DEL 2025
B6: CONCEPTO | D6: IMPORTE
B7: CONTRATADO A LA FECHA | D7: =159394.09*1.16 -> 184897.14
B8: COBRADO | D8: 92449.58
B9: POR COBRAR | D9: =+D7-D8 -> 92447.564
B10: FONDO DE GARANTIA | D10: 0
B11: LQUIDO POR COBRAR | D11: =+D9-D10 -> 92447.564
A13: N° | B13: FECHA | C13: N° FACTURA | D13: CONCEPTO | E13: IMPORTE A COBRAR | F13: IMPORTE COBRADO | G13: SALDO POR COBRAR | H13: FECHA DE PAGO
E15: =+E14 -> 0 | F15: =+F140 -> 0 | G15: =+G14 -> 0

Sheet BANBAJIO
A2: COMPAÑÍA: | B2: HEG DISEÑO E INSTALACION SA DE CV
A3: CONCEPTO: | B3: FACTURAS PENDIENTES DE COBRO DEL PROYECTO BANBAJIO 2024
A4: FECHA: | B4: 17 DE ENERO DEL 2025
B6: CONCEPTO | D6: IMPORTE
B7: CONTRATADO A LA FECHA | D7: 696000
B8: COBRADO | D8: 522000
B9: POR COBRAR | D9: =+D7-D8 -> 174000
B10: FONDO DE GARANTIA | D10: 0
B11: LQUIDO POR COBRAR | D11: =+D9-D10 -> 174000
A13: N° | B13: FECHA | C13: N° FACTURA | D13: CONCEPTO | E13: IMPORTE A COBRAR | F13: IMPORTE COBRADO | G13: SALDO POR COBRAR | H13: FECHA DE PAGO
E15: =+E14 -> 0 | F15: =+F14 -> 0 | G15: =+G14 -> 0

Sheet BEITI
A2: COMPAÑÍA: | B2: HEG DISEÑO E INSTALACION SA DE CV
A3: CONCEPTO: | B3: FACTURAS PENDIENTES DE COBRO DEL PROYECTO BEITI
A4: FECHA: | B4: 30 DE SEPTIEMBRE DEL 2025
B6: CONCEPTO | D6: IMPORTE
B7: CONTRATADO A LA FECHA | D7: 19122789
B8: COBRADO | D8: 16634790
B9: POR COBRAR | D9: =+D7-D8 -> 2487999.1
B10: FONDO DE GARANTIA 3% | D10: =+D7*3% -> 573683.68
B11: LQUIDO POR COBRAR | D11: =+D9-D10 -> 1914315.4
A13: N° | B13: FECHA | C13: N° FACTURA | D13: CONCEPTO | E13: IMPORTE A COBRAR | F13: IMPORTE COBRADO | G13: SALDO POR COBRAR | H13: FECHA DE PAGO
A14: 1 | B14: 45901 | C14: 4295 | D14: EST 29 | E14: 138814.33 | F14: 0 | G14: 138814.33
A15: 2 | B15: 45922 | C15: 4314 | D15: EST 30 | E15: 54753.73 | F15: 0 | G15: 54753.73
E16: =+E14+E15 -> 193568.06 | F16: =+F14+F15 -> 0 | G16: =+G14+G15 -> 193568.06

Sheet BEITI MUESTRA
A2: COMPAÑÍA: | B2: HEG DISEÑO E INSTALACION SA DE CV
A3: CONCEPTO: | B3: FACTURAS PENDIENTES DE COBRO DEL PROYECTO BEITI MUESTRA
A4: FECHA: | B4: 02 DE AGOSTO DEL 2024
B6: CONCEPTO | D6: IMPORTE
B7: CONTRATADO A LA FECHA | D7: 130408.4
B8: COBRADO | D8: 91285.88
B9: POR COBRAR | D9: =+D7-D8 -> 39122.52
B10: FONDO DE GARANTIA | D10: 0
B11: LQUIDO POR COBRAR | D11: =+D9-D10 -> 39122.52
A13: N° | B13: FECHA | C13: N° FACTURA | D13: CONCEPTO | E13: IMPORTE A COBRAR | F13: IMPORTE COBRADO | G13: SALDO POR COBRAR | H13: FECHA DE PAGO

Sheet CASA DIAZ
A2: COMPAÑÍA: | B2: HEG DISEÑO E INSTALACION SA DE CV
A3: CONCEPTO: | B3: FACTURAS PENDIENTES DE COBRO DEL PROYECTO CASA DIAZ
A4: FECHA: | B4: 25 DE AGOSTO DEL 2024
B6: CONCEPTO | D6: IMPORTE
B7: CONTRATADO A LA FECHA | D7: 661711.19
B8: COBRADO | D8: =401565.91+182101.7 -> 583667.61
B9: POR COBRAR | D9: =+D7-D8 -> 78043.579
B10: FONDO DE GARANTIA | D10: 0
B11: LQUIDO POR COBRAR | D11: =+D9-D10 -> 78043.579
A13: N° | B13: FECHA | C13: N° FACTURA | D13: CONCEPTO | E13: IMPORTE A COBRAR | F13: IMPORTE COBRADO | G13: SALDO POR COBRAR | H13: FECHA DE PAGO
E15: =SUM(E14) -> 0 | F15: =SUM(F14) -> 0 | G15: =SUM(G14) -> 0

Sheet COM TECNO DISTRIB MOSO
A2: COMPAÑÍA: | B2: HEG DISEÑO E INSTALACION SA DE CV
A3: CONCEPTO: | B3: FACTURAS PENDIENTES DE COBRO DEL PROYECTO COMISIONES TECNOVIDRIO
A4: FECHA: | B4: 17 DE SEPTIEMBRE DEL 2025
B6: CONCEPTO | D6: IMPORTE
B7: CONTRATADO A LA FECHA | D7: 1160000
B8: COBRADO | D8: 1160000
B9: POR COBRAR | D9: =+D7-D8 -> 0
B10: FONDO DE GARANTIA | D10: 0
B11: LQUIDO POR COBRAR | D11: =+D9-D10 -> 0
A13: N° | B13: FECHA | C13: N° FACTURA | D13: CONCEPTO | E13: IMPORTE A COBRAR | F13: IMPORTE COBRADO | G13: SALDO POR COBRAR | H13: FECHA DE PAGO

Sheet COM TECNO
A2: COMPAÑÍA: | B2: HEG DISEÑO E INSTALACION SA DE CV
A3: CONCEPTO: | B3: FACTURAS PENDIENTES DE COBRO DEL PROYECTO COMISIONES TECNOVIDRIO
A4: FECHA: | B4: 17 DE SEPTIEMBRE DEL 2025
B6: CONCEPTO | D6: IMPORTE
B7: CONTRATADO A LA FECHA | D7: 3215482.2
B8: COBRADO | D8: 0
B9: POR COBRAR | D9: =+D7-D8 -> 3215482.2
B10: FONDO DE GARANTIA | D10: 0
B11: LQUIDO POR COBRAR | D11: =+D9-D10 -> 3215482.2
A13: N° | B13: FECHA | C13: N° FACTURA | D13: CONCEPTO | E13: IMPORTE A COBRAR | F13: IMPORTE COBRADO | G13: SALDO POR COBRAR | H13: FECHA DE PAGO

Sheet C BOSQUE DE OLMOS
A2: COMPAÑÍA: | B2: HEG DISEÑO E INSTALACION SA DE CV
A3: CONCEPTO: | B3: FACTURAS PENDIENTES DE COBRO DEL PROYECTO CASA BOSQUE DE OLMOS
A4: FECHA: | B4: 27 DE ENERO DEL 2025
B6: CONCEPTO | D6: IMPORTE
B7: CONTRATADO A LA FECHA | D7: 2378000
B8: COBRADO | D8: 1664600
B9: POR COBRAR | D9: =+D7-D8 -> 713400
B10: FONDO DE GARANTIA | D10: 0
B11: LQUIDO POR COBRAR | D11: =+D9-D10 -> 713400
A13: N° | B13: FECHA | C13: N° FACTURA | D13: CONCEPTO | E13: IMPORTE A COBRAR | F13: IMPORTE COBRADO | G13: SALDO POR COBRAR | H13: FECHA DE PAGO
E15: =SUM(E14) -> 0 | F15: =SUM(F14) -> 0 | G15: =SUM(G14) -> 0

Sheet COLIMA 426
A2: COMPAÑÍA: | B2: HEG DISEÑO E INSTALACION SA DE CV
A3: CONCEPTO: | B3: FACTURAS PENDIENTES DE COBRO DEL PROYECTO COLIMA 426
A4: FECHA: | B4: 02 DE AGOSTO DEL 2024
B6: CONCEPTO | D6: IMPORTE
B7: CONTRATADO A LA FECHA | D7: 426201.95
B8: COBRADO | D8: 298341.36
B9: POR COBRAR | D9: =+D7-D8 -> 127860.59
B10: FONDO DE GARANTIA | D10: 0
B11: LQUIDO POR COBRAR | D11: =+D9-D10 -> 127860.59
A13: N° | B13: FECHA | C13: N° FACTURA | D13: CONCEPTO | E13: IMPORTE A COBRAR | F13: IMPORTE COBRADO | G13: SALDO POR COBRAR | H13: FECHA DE PAGO

Sheet CONSTITUYENTES 7
A2: COMPAÑÍA: | B2: HEG DISEÑO E INSTALACION SA DE CV
A3: CONCEPTO: | B3: FACTURAS PENDIENTES DE COBRO DEL PROYECTO CONSTITUYENTES 7
A4: FECHA: | B4: 30 DE SEPTIEMBRE DEL 2025
B6: CONCEPTO | D6: IMPORTE
B7: CONTRATADO A LA FECHA | D7: 1857290.5
B8: COBRADO | D8: 500000
B9: POR COBRAR | D9: =+D7-D8 -> 1357290.5
B10: FONDO DE GARANTIA | D10: 0
B11: LQUIDO POR COBRAR | D11: =+D9-D10 -> 1357290.5
A13: N° | B13: FECHA | C13: N° FACTURA | D13: CONCEPTO | E13: IMPORTE A COBRAR | F13: IMPORTE COBRADO | G13: SALDO POR COBRAR | H13: FECHA DE PAGO
A14: 1 | B14: 45922 | C14: 4313 | D14: EST 01 | E14: 334083.85 | F14: 0 | G14: 334083.85
E15: =SUM(E14) -> 334083.85 | F15: =SUM(F14) -> 0 | G15: =SUM(G14) -> 334083.85

Sheet CV GYM
A2: COMPAÑÍA: | B2: HEG DISEÑO E INSTALACION SA DE CV
A3: CONCEPTO: | B3: FACTURAS PENDIENTES DE COBRO DEL PROYECTO COSTAVENTURA GYM
A4: FECHA: | B4: 19 DE SEPTIEMBRE DEL 2025
B6: CONCEPTO | D6: IMPORTE
B7: CONTRATADO A LA FECHA | D7: 1475327.4
B8: COBRADO | D8: =1127328.14 -> 1127328.1
B9: POR COBRAR | D9: =+D7-D8 -> 347999.23
B10: FONDO DE GARANTIA | D10: 0
B11: LQUIDO POR COBRAR | D11: =+D9-D10 -> 347999.23
A13: N° | B13: FECHA | C13: N° FACTURA | D13: CONCEPTO | E13: IMPORTE A COBRAR | F13: IMPORTE COBRADO | G13: SALDO POR COBRAR | H13: FECHA DE PAGO
E15: =SUM(E14) -> 0 | F15: =SUM(F14) -> 0 | G15: =SUM(G14) -> 0

Sheet CV SUPERVISION
A2: COMPAÑÍA: | B2: HEG DISEÑO E INSTALACION SA DE CV
A3: CONCEPTO: | B3: FACTURAS PENDIENTES DE COBRO DEL PROYECTO COSTAVENTURA GYM
A4: FECHA: | B4: 16 DE DICIEMBRE DEL 2024
B6: CONCEPTO | D6: IMPORTE
B7: CONTRATADO A LA FECHA | D7: 116000
B8: COBRADO | D8: =92800+23200 -> 116000
B9: POR COBRAR | D9: =+D7-D8 -> 0
B10: FONDO DE GARANTIA | D10: 0
B11: LQUIDO POR COBRAR | D11: =+D9-D10 -> 0
A13: N° | B13: FECHA | C13: N° FACTURA | D13: CONCEPTO | E13: IMPORTE A COBRAR | F13: IMPORTE COBRADO | G13: SALDO POR COBRAR | H13: FECHA DE PAGO
E15: =SUM(E14) -> 0 | F15: =SUM(F14) -> 0 | G15: =SUM(G14) -> 0

Sheet DECK POLANCO
A2: COMPAÑÍA: | B2: HEG DISEÑO E INSTALACION SA DE CV
A3: CONCEPTO: | B3: FACTURAS PENDIENTES DE COBRO DEL PROYECTO DECK POLANCO
A4: FECHA: | B4: 02 DE AGOSTO DEL 2024
B6: CONCEPTO | D6: IMPORTE
B7: CONTRATADO A LA FECHA | D7: 577461.22
B8: COBRADO | D8: 313200
B9: POR COBRAR | D9: =+D7-D8 -> 264261.22
B10: FONDO DE GARANTIA | D10: 0
B11: LQUIDO POR COBRAR | D11: =+D9-D10 -> 264261.22
A13: N° | B13: FECHA | C13: N° FACTURA | D13: CONCEPTO | E13: IMPORTE A COBRAR | F13: IMPORTE COBRADO | G13: SALDO POR COBRAR | H13: FECHA DE PAGO

Sheet EDITION KANAI
A2: COMPAÑÍA: | B2: HEG DISEÑO E INSTALACION SA DE CV
A3: CONCEPTO: | B3: FACTURAS PENDIENTES DE COBRO DEL PROYECTO EDITION KANAI
A4: FECHA: | B4: 02 DE AGOSTO DEL 2024
B6: CONCEPTO | D6: IMPORTE
B7: CONTRATADO A LA FECHA | D7: 43754583
B8: COBRADO | D8: 41364024
B9: POR COBRAR | D9: =+D7-D8 -> 2390558.7
B10: FONDO DE GARANTIA 5% | D10: =+D7*5% -> 2187729.2
B11: LQUIDO POR COBRAR | D11: =+D9-D10 -> 202829.58
A13: N° | B13: FECHA | C13: N° FACTURA | D13: CONCEPTO | E13: IMPORTE A COBRAR | F13: IMPORTE COBRADO | G13: SALDO POR COBRAR | H13: FECHA DE PAGO
E15: =SUM(E14) -> 0 | F15: =SUM(F14) -> 0 | G15: =SUM(G14) -> 0

Sheet ED LIMPIEZA MOSO
A2: COMPAÑÍA: | B2: HEG DISEÑO E INSTALACION SA DE CV
A3: CONCEPTO: | B3: FACTURAS PENDIENTES DE COBRO DEL PROYECTO EDITION LIMPIEZA MOSO
A4: FECHA: | B4: 16 DE AGOSTO DEL 2024
B6: CONCEPTO | D6: IMPORTE
B7: CONTRATADO A LA FECHA | D7: 4858114.8
B8: COBRADO | D8: 4858114.8
B9: POR COBRAR | D9: =+D7-D8 -> 0
B10: FONDO DE GARANTIA | D10: 0
B11: LQUIDO POR COBRAR | D11: =+D9-D10 -> 0
A13: N° | B13: FECHA | C13: N° FACTURA | D13: CONCEPTO | E13: IMPORTE A COBRAR | F13: IMPORTE COBRADO | G13: SALDO POR COBRAR | H13: FECHA DE PAGO
E15: =+E14 -> 0 | F15: =+F14 -> 0 | G15: =+G14 -> 0
D17: EQ EN MN (TC 17.50) | E17: =+E15*17.5 -> 0 | F17: =+F15*17.5 -> 0 | G17: =+G15*17.5 -> 0

Sheet EDITION KANAI X-TREME
A2: COMPAÑÍA: | B2: HEG DISEÑO E INSTALACION SA DE CV
A3: CONCEPTO: | B3: FACTURAS PENDIENTES DE COBRO DEL PROYECTO EDITION KANAI X-TREME
A4: FECHA: | B4: 13 DE MARZO DEL 2025
B6: CONCEPTO | D6: IMPORTE
B7: CONTRATADO A LA FECHA | D7: 27519818
B8: COBRADO | D8: 26992714
B9: POR COBRAR | D9: =+D7-D8 -> 527104.36
B10: FONDO DE GARANTIA | D10: 0
B11: LQUIDO POR COBRAR | D11: =+D9-D10 -> 527104.36
A13: N° | B13: FECHA | C13: N° FACTURA | D13: CONCEPTO | E13: IMPORTE A COBRAR | F13: IMPORTE COBRADO | G13: SALDO POR COBRAR | H13: FECHA DE PAGO
E15: =SUM(E14) -> 0 | F15: =SUM(F14) -> 0 | G15: =SUM(G14) -> 0
G16: =+G15*20 -> 0

Sheet EMPORIO ACAPULCO
A2: COMPAÑÍA: | B2: HEG DISEÑO E INSTALACION SA DE CV
A3: CONCEPTO: | B3: FACTURAS PENDIENTES DE COBRO DEL PROYECTO EMPORIO ACAPULCO
A4: FECHA: | B4: 09 DE SEPTIEMBRE DEL 2025
B6: CONCEPTO | D6: IMPORTE
B7: CONTRATADO A LA FECHA | D7: 4921927
B8: COBRADO | D8: =4044335.52+163958.58+19861.72 -> 4228155.8
B9: POR COBRAR | D9: =+D7-D8 -> 693771.22
B10: FONDO DE GARANTIA 10% | D10: =+D7*10% -> 492192.7
B11: LQUIDO POR COBRAR | D11: =+D9-D10 -> 201578.52
A13: N° | B13: FECHA | C13: N° FACTURA | D13: CONCEPTO | E13: IMPORTE A COBRAR | F13: IMPORTE COBRADO | G13: SALDO POR COBRAR | H13: FECHA DE PAGO
E15: =+E14 -> 0 | F15: =+F14 -> 0 | G15: =+G14 -> 0

Sheet EMPORIO CANC TORRE R
A2: COMPAÑÍA: | B2: HEG DISEÑO E INSTALACION SA DE CV
A3: CONCEPTO: | B3: FACTURAS PENDIENTES DE COBRO DEL PROYECTO EMPORIO ACAPULCO
A4: FECHA: | B4: 23 DE SEPTIEMBRE DEL 2025
B6: CONCEPTO | D6: IMPORTE
B7: CONTRATADO A LA FECHA | D7: 53511407
B8: COBRADO | D8: 20106844
B9: POR COBRAR | D9: =+D7-D8 -> 33404563
B10: FONDO DE GARANTIA 10% | D10: =+D7*10% -> 5351140.7
B11: LQUIDO POR COBRAR | D11: =+D9-D10 -> 28053422
A13: N° | B13: FECHA | C13: N° FACTURA | D13: CONCEPTO | E13: IMPORTE A COBRAR | F13: IMPORTE COBRADO | G13: SALDO POR COBRAR | H13: FECHA DE PAGO
E15: =SUM(E14) -> 0 | F15: =SUM(F14) -> 0 | G15: =SUM(G14) -> 0

Sheet FAIRMONT ACAPULCO
A2: COMPAÑÍA: | B2: HEG DISEÑO E INSTALACION SA DE CV
A3: CONCEPTO: | B3: FACTURAS PENDIENTES DE COBRO DEL PROYECTO FAIRMONT ACAPULCO
A4: FECHA: | B4: 29 DE SEPTIEMBRE DEL 2025
B6: CONCEPTO | D6: IMPORTE
B7: CONTRATADO A LA FECHA | D7: =27857430.6472+426871.47 -> 28284302
B8: COBRADO | D8: =27141397.12+158884.91+426871.47 -> 27727154
B9: POR COBRAR | D9: =+D7-D8 -> 557148.62
B10: FONDO DE GARANTIA 2% | D10: =534500.14+22648.47 -> 557148.61
B11: LQUIDO POR COBRAR | D11: =+D9-D10 -> 0.0071999984
A13: N° | B13: FECHA | C13: N° FACTURA | D13: CONCEPTO | E13: IMPORTE A COBRAR | F13: IMPORTE COBRADO | G13: SALDO POR COBRAR | H13: FECHA DE PAGO
E15: =SUM(E14) -> 0 | F15: =SUM(F14) -> 0 | G15: =SUM(G14) -> 0

Sheet FLOW
A2: COMPAÑÍA: | B2: HEG DISEÑO E INSTALACION SA DE CV
A3: CONCEPTO: | B3: FACTURAS PENDIENTES DE COBRO DEL PROYECTO FLOW
A4: FECHA: | B4: 08 DE SEPTIEMBRE DEL 2025
B6: CONCEPTO | D6: IMPORTE
B7: CONTRATADO A LA FECHA | D7: =53542531.9992+89038.49 -> 53631570
B8: COBRADO | D8: =49735616.11+100000+250000+100000+100000 -> 50285616
B9: POR COBRAR | D9: =+D7-D8 -> 3345954.4
B10: FONDO DE GARANTIA | D10: 0
B11: LQUIDO POR COBRAR | D11: =+D9-D10 -> 3345954.4
A13: N° | B13: FECHA | C13: N° FACTURA | D13: CONCEPTO | E13: IMPORTE A COBRAR | F13: IMPORTE COBRADO | G13: SALDO POR COBRAR | H13: FECHA DE PAGO

Sheet FLOW 2025
A2: COMPAÑÍA: | B2: HEG DISEÑO E INSTALACION SA DE CV
A3: CONCEPTO: | B3: FACTURAS PENDIENTES DE COBRO DEL PROYECTO FLOW
A4: FECHA: | B4: 12 DE SEPTIEMBRE DEL 2025
B6: CONCEPTO | D6: IMPORTE
B7: CONTRATADO A LA FECHA | D7: 818274.32
B8: COBRADO | D8: =291447.33+82639.61+86301.63+45345.82 -> 505734.39
B9: POR COBRAR | D9: =+D7-D8 -> 312539.93
B10: FONDO DE GARANTIA | D10: 0
B11: LQUIDO POR COBRAR | D11: =+D9-D10 -> 312539.93
A13: N° | B13: FECHA | C13: N° FACTURA | D13: CONCEPTO | E13: IMPORTE A COBRAR | F13: IMPORTE COBRADO | G13: SALDO POR COBRAR | H13: FECHA DE PAGO
E15: =+E14 -> 0 | F15: 0 | G15: =+G14 -> 0

Sheet GHC
A2: COMPAÑÍA: | B2: HEG DISEÑO E INSTALACION SA DE CV
A3: CONCEPTO: | B3: FACTURAS PENDIENTES DE COBRO DEL PROYECTO GRAND HYATT CANCUN
A4: FECHA: | B4: 29 DE AGOSTO DEL 2025
B6: CONCEPTO | D6: IMPORTE
B7: CONTRATADO A LA FECHA | D7: 1.4669845e+08
B8: COBRADO | D8: =90929473.01+370526.41 -> 91299999
B9: POR COBRAR | D9: =+D7-D8 -> 55398446
B10: FONDO DE GARANTIA 10% | D10: =+D7*10% -> 14669845
B11: LQUIDO POR COBRAR | D11: =+D9-D10 -> 40728602
A13: N° | B13: FECHA | C13: N° FACTURA | D13: CONCEPTO | E13: IMPORTE A COBRAR | F13: IMPORTE COBRADO | G13: SALDO POR COBRAR | H13: FECHA DE PAGO
E15: =SUM(E14) -> 0 | F15: =SUM(F14) -> 0 | G15: =SUM(G14) -> 0

Sheet  GHC MOSO
A2: COMPAÑÍA: | B2: HEG DISEÑO E INSTALACION SA DE CV
A3: CONCEPTO: | B3: FACTURAS PENDIENTES DE COBRO DEL PROYECTO GRAND HYATT CANCUN MOSO
A4: FECHA: | B4: 06 DE OCTUBRE DEL 2025
B6: CONCEPTO | D6: IMPORTE
B7: CONTRATADO A LA FECHA | D7: =6919587.97*1.16 -> 8026722
B8: COBRADO | D8: 0
B9: POR COBRAR | D9: =+D7-D8 -> 8026722
B10: FONDO DE GARANTIA %
B11: LQUIDO POR COBRAR | D11: =+D9-D10 -> 8026722
A13: N° | B13: FECHA | C13: N° FACTURA | D13: CONCEPTO | E13: IMPORTE A COBRAR | F13: IMPORTE COBRADO | G13: SALDO POR COBRAR | H13: FECHA DE PAGO
A14: 1 | B14: 45936 | C14: 4323 | D14: ANTICIPO 70% | E14: 5618705.4 | F14: 0 | G14: 5618705.4
E15: =SUM(E14) -> 5618705.4 | F15: =SUM(F14) -> 0 | G15: =SUM(G14) -> 5618705.4

Sheet HOTEL COPACABANA
A2: COMPAÑÍA: | B2: HEG DISEÑO E INSTALACION SA DE CV
A3: CONCEPTO: | B3: FACTURAS PENDIENTES DE COBRO DEL PROYECTO HOTEL COPACABANA
A4: FECHA: | B4: 12 DESEPTIEMBRE DEL 2025
B6: CONCEPTO | D6: IMPORTE
B7: CONTRATADO A LA FECHA | D7: 28840306
B8: COBRADO | D8: 25293839
B9: POR COBRAR | D9: =+D7-D8 -> 3546467.1
B10: FONDO DE GARANTIA 10% | D10: =+D7*10% -> 2884030.6
B11: LQUIDO POR COBRAR | D11: =+D9-D10 -> 662436.45
A13: N° | B13: FECHA | C13: N° FACTURA | D13: CONCEPTO | E13: IMPORTE A COBRAR | F13: IMPORTE COBRADO | G13: SALDO POR COBRAR | H13: FECHA DE PAGO
A14: 1 | B14: 45832 | C14: 4208 | D14: 5 PAGO 3 ADDENDUM | E14: 1000000 | F14: =100000*5 -> 500000 | G14: =+E14-F14 -> 500000.01
E15: =SUM(E14) -> 1000000 | F15: =SUM(F14) -> 500000 | G15: =SUM(G14) -> 500000.01

Sheet JAIME NUNO
A2: COMPAÑÍA: | B2: HEG DISEÑO E INSTALACION SA DE CV
A3: CONCEPTO: | B3: FACTURAS PENDIENTES DE COBRO DEL PROYECTO JAIME NUNO
A4: FECHA: | B4: 23 DE SEPTIEMBRE DEL 2025
B6: CONCEPTO | D6: IMPORTE
B7: CONTRATADO A LA FECHA | D7: 61450000
B8: COBRADO | D8: 51982458
B9: POR COBRAR | D9: =+D7-D8 -> 9467542.5
B10: FONDO DE GARANTIA | D10: 0
B11: LQUIDO POR COBRAR | D11: =+D9-D10 -> 9467542.5
A13: N° | B13: FECHA | C13: N° FACTURA | D13: CONCEPTO | E13: IMPORTE A COBRAR | F13: IMPORTE COBRADO | G13: SALDO POR COBRAR | H13: FECHA DE PAGO
E15: =SUM(E14) -> 0 | F15: =SUM(F14) -> 0 | G15: =SUM(G14) -> 0

Sheet LANDMARK GDL RESIDENCIAL
A2: COMPAÑÍA: | B2: HEG DISEÑO E INSTALACION SA DE CV
A3: CONCEPTO: | B3: FACTURAS PENDIENTES DE COBRO DEL PROYECTO LANDMARK GUADALAJARA RESIDENCIAL
A4: FECHA: | B4: 23 DE SEPTIEMBRE DEL 2025
B6: CONTRATADO A LA FECHA | D6: IMPORTE
B7: RESIDENCIAL | D7: 37721137
B8: COBRADO | D8: =34122304.83+500000 -> 34622305
B9: POR COBRAR | D9: =+D7-D8 -> 3098831.8
B10: FONDO DE GARANTIA 14.2% | D10: =+D7*14.2%-1000000*2 -> 3356401.4
B11: LIQUIDO POR COBRAR | D11: =+D9-D10 -> -257569.6
A14: N° | B14: FECHA | C14: N° FACTURA | D14: CONCEPTO | E14: IMPORTE A COBRAR | F14: IMPORTE COBRADO | G14: SALDO POR COBRAR | H14: FECHA DE PAGO | I14: PERIODO
A15: 1 | B15: 45196 | C15: 3612 | D15: EST 22 | E15: 232612.83 | F15: 266846.17 | G15: -34233.34 | H15: TE 20/10/2023 | I15: 02/09/2023 AL 08/09/2023
E16: =SUM(E15:E15) -> 232612.83 | F16: =SUM(F15:F15) -> 266846.17 | G16: =SUM(G15:G15) -> -34233.34
G18: FORMULO
G20: ING. CARMEN VILLACORTA

Sheet LANDMARK COMERCIO
A2: COMPAÑÍA: | B2: HEG DISEÑO E INSTALACION SA DE CV
A3: CONCEPTO: | B3: FACTURAS PENDIENTES DE COBRO DEL PROYECTO LANDMARK GUADALAJARA COMERCIO
A4: FECHA: | B4: 30 DE JUNIO DEL 2025
B6: CONTRATADO A LA FECHA | D6: IMPORTE
B7: COMERCIO | D7: 5328863.4
B8: COBRADO | D8: 5080459.4
B9: POR COBRAR | D9: =+D7-D8 -> 248403.96
B10: FONDO DE GARANTIA
B11: LIQUIDO POR COBRAR | D11: =+D9-D10 -> 248403.96
A14: N° | B14: FECHA | C14: N° FACTURA | D14: CONCEPTO | E14: IMPORTE A COBRAR | F14: IMPORTE COBRADO | G14: SALDO POR COBRAR | H14: FECHA DE PAGO | I14: PERIODO
E16: =+E15 -> 0 | F16: =+F15 -> 0 | G16: =+G15 -> 0
G18: FORMULO
G20: ING. CARMEN VILLACORTA

Sheet LANDMARK TIJUANA RES
A2: COMPAÑÍA: | B2: HEG DISEÑO E INSTALACION SA DE CV
A3: CONCEPTO: | B3: PROGRAMA DE PAGOS PARA EL PROYECTO LANDMARK TIJUANA RESIDENCIAL
A4: FECHA: | B4: 13 DE OCTUBRE DEL 2025
B6: CONTRATADO A LA FECHA | D6: IMPORTE CON IVA
B7: MANO DE OBRA | D7: 11187434
B8: COBRADO | D8: 4254490.1
B9: POR COBRAR | D9: =+D7-D8 -> 6932943.8
B10: FONDO DE GARANTIA | D10: =1854662 -> 1854662
B11: LQUIDO POR COBRAR | D11: =+D9-D10 -> 5078281.8
A14: N° | B14: FECHA | C14: N° FACTURA | D14: CONCEPTO | E14: IMPORTE A COBRAR | F14: IMPORTE COBRADO | G14: SALDO POR COBRAR | H14: FECHA DE PAGO | I14: PERIODO
A15: 1 | B15: 45779 | C15: 4143 | D15: EST 22 | E15: 209125.7 | F15: 0 | G15: =+E15-F15 -> 209125.7 | I15: 29/03/2025 AL 18/04/2025
A16: 2 | B16: 45796 | C16: 4159 | D16: EST 23 | E16: 150898.02 | F16: 0 | G16: =+E16-F16 -> 150898.02 | I16: 19/04/2025 AL 02/05/2025
A17: 3 | B17: 45786 | C17: 4183 | D17: EST 24 | E17: 133392.61 | F17: 0 | G17: =+E17-F17 -> 133392.61 | I17: 03/05/2025 AL 23/05/2025
A18: 4 | B18: 45891 | C18: 4282 | D18: EST 25 | E18: 692949.07 | F18: 0 | G18: =+E18-F18 -> 692949.07 | I18: 24/05/2025 AL 08/08/2025
A19: 5 | B19: 45898 | C19: 4292 | D19: EST 26 | E19: 256394.1 | F19: 0 | G19: =+E19-F19 -> 256394.1 | I19: 09/08/2025 AL 15/08/2025
A20: 6 | C20: PENDIENTE | D20: EST 27 | E20: 192295.58 | F20: 0 | G20: =+E20-F20 -> 192295.58 | I20: 16/08/2025 AL 05/09/2025
A21: 7 | C21: PENDIENTE | D21: EST 28 | E21: 334827.59 | F21: 0 | G21: =+E21-F21 -> 334827.59 | I21: 06/09/2025 AL 12/09/2025
A22: 8 | C22: PENDIENTE | D22: ANTICIPO OC-01 | E22: =10728.61*0.6 -> 6437.166 | F22: 0 | G22: =+E22-F22 -> 6437.166
A23: 9 | C23: PENDIENTE | D23: ANTICIPO OC-02 | E23: =2272408.86*0.6 -> 1363445.3 | F23: 0 | G23: =+E23-F23 -> 1363445.3
E24: =SUM(E15:E23) -> 3339765.2 | F24: =SUM(F15:F23) -> 0 | G24: =SUM(G15:G23) -> 3339765.2
G26: FORMULO
G28: ING. CARMEN VILLACORTA

Sheet LANDMARK TIJUANA INTERIORES
A2: COMPAÑÍA: | B2: HEG DISEÑO E INSTALACION SA DE CV
A3: CONCEPTO: | B3: PROGRAMA DE PAGOS PARA EL PROYECTO LANDMARK TIJUANA INTERIORES
A4: FECHA: | B4: 13 DE OCTUBRE DEL 2025
B6: CONTRATADO A LA FECHA | D6: IMPORTE CON IVA
B7: INTERIORES | D7: 5850000
B8: COBRADO | D8: 3510000
B9: POR COBRAR | D9: =+D7-D8 -> 2340000
B10: FONDO DE GARANTIA 5% | D10: =+D7*5% -> 292500
B11: LQUIDO POR COBRAR | D11: =+D9-D10 -> 2047500
A14: N° | B14: FECHA | C14: N° FACTURA | D14: CONCEPTO | E14: IMPORTE A COBRAR | F14: IMPORTE COBRADO | G14: SALDO POR COBRAR | H14: FECHA DE PAGO | I14: PERIODO
A15: 1 | B15: 45817 | C15: 4182 | D15: EST 01 | E15: 153017.84 | F15: 0 | G15: 153017.84 | I15: 03/05/2025 AL 23/05/2025
A16: 2 | B16: 45837 | C16: 4213 | D16: EST 02 | E16: 153017.84 | F16: 0 | G16: 153017.84 | I16: 24/05/2025 AL 13/06/2025
A17: 3 | B17: 45814 | C17: 4223 | D17: EST 03 | E17: 153017.84 | F17: 0 | G17: 153017.84 | I17: 14/06/2025 AL 20/06/2025
A18: 4 | B18: 45850 | C18: 4231 | D18: EST 04 | E18: 153017.84 | F18: 0 | G18: 153017.84 | I18: 21/06/2025 AL 27/06/2026
A19: 5 | B19: 45858 | C19: 4234 | D19: EST 05 | E19: 153017.84 | F19: 0 | G19: 153017.84 | I19: 28/06/2025 AL 04/07/2025
A20: 6 | B20: 45870 | C20: 4249 | D20: EST 06 | E20: 153017.84 | F20: 0 | G20: 153017.84 | I20: 05/07/2025 AL 18/07/2025
A21: 7 | B21: 45898 | C21: 4291 | D21: EST 07 | E21: 87709.48 | F21: 0 | G21: 87709.48 | I21: 19/07/2025 AL 15/08/2025
E22: =SUM(E15:E21) -> 1005816.5 | F22: =SUM(F15:F21) -> 0 | G22: =SUM(G15:G21) -> 1005816.5
G24: FORMULO
G26: ING. CARMEN VILLACORTA

Sheet MARIANO ESCOBEDO
A2: COMPAÑÍA: | B2: HEG DISEÑO E INSTALACION SA DE CV
A3: CONCEPTO: | B3: FACTURAS PENDIENTES DE COBRO DEL PROYECTO MARIANO ESCOBEDO 350
A4: FECHA: | B4: 11 DE JULIO DEL 2025
B6: CONCEPTO | D6: IMPORTE
B7: CONTRATADO A LA FECHA | D7: 38824118
B8: COBRADO | D8: 32373000
B9: POR COBRAR | D9: =+D7-D8 -> 6451118.1
B10: FONDO DE GARANTIA | D10: 0
B11: LQUIDO POR COBRAR | D11: =+D9-D10 -> 6451118.1
A13: N° | B13: FECHA | C13: N° FACTURA | D13: CONCEPTO | E13: IMPORTE A COBRAR | F13: IMPORTE COBRADO | G13: SALDO POR COBRAR | H13: FECHA DE PAGO
E15: =SUM(E14) -> 0 | F15: =SUM(F14) -> 0 | G15: =SUM(G14) -> 0

Sheet MAURICIO CAPON
A2: COMPAÑÍA: | B2: HEG DISEÑO E INSTALACION SA DE CV
A3: CONCEPTO: | B3: FACTURAS PENDIENTES DE COBRO DEL PROYECTO MAURICIO CAPON
A4: FECHA: | B4: 09 DE ABRIL DEL 2025
B6: CONCEPTO | D6: IMPORTE
B7: CONTRATADO A LA FECHA | D7: 3737883.4
B8: COBRADO | D8: 1868941.1
B9: POR COBRAR | D9: =+D7-D8 -> 1868942.3
B10: FONDO DE GARANTIA | D10: 0
B11: LQUIDO POR COBRAR | D11: =+D9-D10 -> 1868942.3
A13: N° | B13: FECHA | C13: N° FACTURA | D13: CONCEPTO | E13: IMPORTE A COBRAR | F13: IMPORTE COBRADO | G13: SALDO POR COBRAR | H13: FECHA DE PAGO
E15: =SUM(E14) -> 0 | F15: =SUM(F14) -> 0 | G15: =SUM(G14) -> 0

Sheet MITIKAH
A2: COMPAÑÍA: | B2: HEG DISEÑO E INSTALACION SA DE CV
A3: CONCEPTO: | B3: FACTURAS PENDIENTES DE COBRO DEL PROYECTO MITIKAH
A4: FECHA: | B4: 29 DE SEPTIEMBRE DEL 2025
B6: CONCEPTO | D6: IMPORTE
B7: CONTRATADO A LA FECHA | D7: 62149277
B8: COBRADO | D8: 57294037
B9: POR COBRAR | D9: 3666090.1
B10: FONDO DE GARANTIA | D10: 3666090.1
B11: LQUIDO POR COBRAR | D11: =+D9-D10 -> 0
A13: N° | B13: FECHA | C13: N° FACTURA | D13: CONCEPTO | E13: IMPORTE A COBRAR | F13: IMPORTE COBRADO | G13: SALDO POR COBRAR | H13: FECHA DE PAGO
E15: =SUM(E14) -> 0 | F15: =SUM(F14) -> 0 | G15: =SUM(G14) -> 0

Sheet MIRALTA
A2: COMPAÑÍA: | B2: HEG DISEÑO E INSTALACION SA DE CV
A3: CONCEPTO: | B3: FACTURAS PENDIENTES DE COBRO DEL PROYECTO MIRALTA
A4: FECHA: | B4: 02 DE AGOSTO DEL 2024
B6: CONCEPTO | D6: IMPORTE
B7: CONTRATADO A LA FECHA | D7: 82516469
B8: COBRADO | D8: =80936447.22+250000 -> 81186447
B9: POR COBRAR | D9: =+D7-D8 -> 1330022
B10: FONDO DE GARANTIA | D10: 0
B11: LQUIDO POR COBRAR | D11: =+D9-D10 -> 1330022
A13: N° | B13: FECHA | C13: N° FACTURA | D13: CONCEPTO | E13: IMPORTE A COBRAR | F13: IMPORTE COBRADO | G13: SALDO POR COBRAR | H13: FECHA DE PAGO

Sheet MONTE AZUL 2024
A2: COMPAÑÍA: | B2: HEG DISEÑO E INSTALACION SA DE CV
A3: CONCEPTO: | B3: FACTURAS PENDIENTES DE COBRO DEL PROYECTO MONTE AZUL 2024
A4: FECHA: | B4: 06 DE MAYO DEL 2025
B6: CONCEPTO | D6: IMPORTE
B7: CONTRATADO A LA FECHA | D7: 2185946.2
B8: COBRADO | D8: 1160000
B9: POR COBRAR | D9: =+D7-D8 -> 1025946.2
B10: FONDO DE GARANTIA | D10: 0
B11: LQUIDO POR COBRAR | D11: =+D9-D10 -> 1025946.2
A13: N° | B13: FECHA | C13: N° FACTURA | D13: CONCEPTO | E13: IMPORTE A COBRAR | F13: IMPORTE COBRADO | G13: SALDO POR COBRAR | H13: FECHA DE PAGO

Sheet MU
A2: COMPAÑÍA: | B2: HEG DISEÑO E INSTALACION SA DE CV
A3: CONCEPTO: | B3: FACTURAS PENDIENTES DE COBRO DEL PROYECTO MONTES URALES
A4: FECHA: | B4: 23 DE SEPTIEMBRE DEL 2024
B6: CONCEPTO | D6: IMPORTE
B7: CONTRATADO A LA FECHA | D7: 20772762
B8: COBRADO | D8: 16914241
B9: POR COBRAR | D9: =+D7-D8 -> 3858520.6
B10: FONDO DE GARANTIA | D10: 0
B11: LQUIDO POR COBRAR | D11: =+D9-D10 -> 3858520.6
A13: N° | B13: FECHA | C13: N° FACTURA | D13: CONCEPTO | E13: IMPORTE A COBRAR | F13: IMPORTE COBRADO | G13: SALDO POR COBRAR | H13: FECHA DE PAGO
E15: =SUM(E14) -> 0 | F15: =SUM(F14) -> 0 | G15: =SUM(G14) -> 0

Sheet MU 2025
A2: COMPAÑÍA: | B2: HEG DISEÑO E INSTALACION SA DE CV
A3: CONCEPTO: | B3: FACTURAS PENDIENTES DE COBRO DEL PROYECTO MONTES URALES 2025
A4: FECHA: | B4: 29 DE AGOSTO DEL 2025
B6: CONCEPTO | D6: IMPORTE
B7: CONTRATADO A LA FECHA | D7: 284540.1
B8: COBRADO | D8: =230616.52+11396.49 -> 242013.01
B9: POR COBRAR | D9: =+D7-D8 -> 42527.09
B10: FONDO DE GARANTIA | D10: 0
B11: LQUIDO POR COBRAR | D11: =+D9-D10 -> 42527.09
A13: N° | B13: FECHA | C13: N° FACTURA | D13: CONCEPTO | E13: IMPORTE A COBRAR | F13: IMPORTE COBRADO | G13: SALDO POR COBRAR | H13: FECHA DE PAGO
E15: =SUM(E14) -> 0 | F15: =SUM(F14) -> 0 | G15: =SUM(G14) -> 0

Sheet NAARA
A2: COMPAÑÍA: | B2: HEG DISEÑO E INSTALACION SA DE CV
A3: CONCEPTO: | B3: FACTURAS PENDIENTES DE COBRO DEL PROYECTO NAARA
A4: FECHA: | B4: 17 DE SEPTIEMBRE DEL 2025
B6: CONCEPTO | D6: IMPORTE
B7: CONTRATADO A LA FECHA | D7: 31198824
B8: COBRADO | D8: 30357849
B9: POR COBRAR | D9: =+D7-D8 -> 840975.81
B10: FONDO DE GARANTIA | D10: =+D7*10%-1022560.39-137437.23-1322969.33-243599.63 -> 393315.86
B11: LQUIDO POR COBRAR | D11: =+D9-D10 -> 447659.95
A13: N° | B13: FECHA | C13: N° FACTURA | D13: CONCEPTO | E13: IMPORTE A COBRAR | F13: IMPORTE COBRADO | G13: SALDO POR COBRAR
E15: =SUM(E14) -> 0 | F15: =SUM(F14) -> 0 | G15: =SUM(G14) -> 0

Sheet NAARA PISO 2
A2: COMPAÑÍA: | B2: HEG DISEÑO E INSTALACION SA DE CV
A3: CONCEPTO: | B3: FACTURAS PENDIENTES DE COBRO DEL PROYECTO NAARA PISO 2
A4: FECHA: | B4: 17 DE SEPTIEMBRE DEL 2025
B6: CONCEPTO | D6: IMPORTE
B7: CONTRATADO A LA FECHA | D7: =209941.82*1.16 -> 243532.51
B8: COBRADO | D8: 170472.59
B9: POR COBRAR | D9: =+D7-D8 -> 73059.921
B10: FONDO DE GARANTIA | D10: 0
B11: LQUIDO POR COBRAR | D11: =+D9-D10 -> 73059.921
A13: N° | B13: FECHA | C13: N° FACTURA | D13: CONCEPTO | E13: IMPORTE A COBRAR | F13: IMPORTE COBRADO | G13: SALDO POR COBRAR
E15: =SUM(E14) -> 0 | F15: =SUM(F14) -> 0 | G15: =SUM(G14) -> 0

Sheet NUA INTERLOMAS
A2: COMPAÑÍA: | B2: HEG DISEÑO E INSTALACION SA DE CV
A3: CONCEPTO: | B3: FACTURAS PENDIENTES DE COBRO DEL PROYECTO NUA INTERLOMAS
A4: FECHA: | B4: 18 DE AGOSTO DEL 2025
B6: CONCEPTO | D6: IMPORTE
B7: CONTRATADO A LA FECHA | D7: 81729902
B8: COBRADO | D8: 74390373
B9: POR COBRAR | D9: =+D7-D8 -> 7339529.8
B10: FONDO DE GARANTIA | D10: 0
B11: LQUIDO POR COBRAR | D11: =+D9-D10 -> 7339529.8
A13: N° | B13: FECHA | C13: N° FACTURA | D13: CONCEPTO | E13: IMPORTE A COBRAR | F13: IMPORTE COBRADO | G13: SALDO POR COBRAR | H13: FECHA DE PAGO
E15: =SUM(E14) -> 0 | F15: =SUM(F14) -> 0 | G15: =SUM(G14) -> 0

Sheet OCEAN CLUB MAT
A2: COMPAÑÍA: | B2: HEG DISEÑO E INSTALACION SA DE CV
A3: CONCEPTO: | B3: FACTURAS PENDIENTES DE COBRO DEL PROYECTO OCEAN CLUB MATERIALES
A4: FECHA: | B4: 18 DE SEPTIEMBRE DEL 2025
B6: CONCEPTO | D6: IMPORTE
B7: CONTRATADO A LA FECHA | D7: 17197639
B8: COBRADO | D8: 17197636
B9: POR COBRAR | D9: =+D7-D8 -> 2.8256
B10: FONDO DE GARANTIA | D10: 0
B11: LQUIDO POR COBRAR | D11: =+D9-D10 -> 2.8256
A13: N° | B13: FECHA | C13: N° FACTURA | D13: CONCEPTO | E13: IMPORTE A COBRAR | F13: IMPORTE COBRADO | G13: SALDO POR COBRAR | H13: FECHA DE PAGO
E15: =SUM(E14) -> 0 | F15: =SUM(F14) -> 0 | G15: =SUM(G14) -> 0

Sheet OCEAN CLUB INST
A2: COMPAÑÍA: | B2: HEG DISEÑO E INSTALACION SA DE CV
A3: CONCEPTO: | B3: FACTURAS PENDIENTES DE COBRO DEL PROYECTO OCEAN CLUB INSTALACION
A4: FECHA: | B4: 10 DE SEPTIEMBRE DEL 2025
B6: CONCEPTO | D6: IMPORTE
B7: CONTRATADO A LA FECHA | D7: 11483545
B8: COBRADO | D8: =8229984.23+580000*2+100000 -> 9489984.2
B9: POR COBRAR | D9: =+D7-D8 -> 1993560.7
B10: FONDO DE GARANTIA | D10: 0
B11: LQUIDO POR COBRAR | D11: =+D9-D10 -> 1993560.7
A13: N° | B13: FECHA | C13: N° FACTURA | D13: CONCEPTO | E13: IMPORTE A COBRAR | F13: IMPORTE COBRADO | G13: SALDO POR COBRAR | H13: FECHA DE PAGO
A14: 1 | B14: 45817 | C14: SDO 4186 | D14: 6 PAGO | E14: =580000 -> 580000 | F14: 100000 | G14: =+E14-F14 -> 480000
E15: =+E14 -> 580000 | F15: =+F14 -> 100000 | G15: =+G14 -> 480000

Sheet PARALLEL
A2: COMPAÑÍA: | B2: HEG DISEÑO E INSTALACION SA DE CV
A3: CONCEPTO: | B3: FACTURAS PENDIENTES DE COBRO DEL PROYECTO PARALLEL
A4: FECHA: | B4: 25 DE JUNIO DEL 2025
B6: CONCEPTO | D6: IMPORTE
B7: CONTRATADO A LA FECHA | D7: 44512359
B8: COBRADO | D8: =42905216.3546497+1043640.34 -> 43948857
B9: POR COBRAR | D9: =+D7-D8 -> 563502.75
B10: FONDO DE GARANTIA | D10: 0
B11: LQUIDO POR COBRAR | D11: =+D9-D10 -> 563502.75
A13: N° | B13: FECHA | C13: N° FACTURA | D13: CONCEPTO | E13: IMPORTE A COBRAR | F13: IMPORTE COBRADO | G13: SALDO POR COBRAR | H13: FECHA DE PAGO
E15: =SUM(E14) -> 0 | F15: =SUM(F14) -> 0 | G15: =SUM(G14) -> 0

Sheet PARALLEL 2025
A2: COMPAÑÍA: | B2: HEG DISEÑO E INSTALACION SA DE CV
A3: CONCEPTO: | B3: FACTURAS PENDIENTES DE COBRO DEL PROYECTO PARALLEL 2025
A4: FECHA: | B4: 18 DE AGOSTO DEL 2025
B6: CONCEPTO | D6: IMPORTE
B7: CONTRATADO A LA FECHA | D7: 794951.41
B8: COBRADO | D8: =290000+145000+29351.41 -> 464351.41
B9: POR COBRAR | D9: =+D7-D8 -> 330600
B10: FONDO DE GARANTIA | D10: 0
B11: LQUIDO POR COBRAR | D11: =+D9-D10 -> 330600
A13: N° | B13: FECHA | C13: N° FACTURA | D13: CONCEPTO | E13: IMPORTE A COBRAR | F13: IMPORTE COBRADO | G13: SALDO POR COBRAR | H13: FECHA DE PAGO
E15: =SUM(E14) -> 0 | F15: =SUM(F14) -> 0 | G15: =SUM(G14) -> 0

Sheet PARALLEL HOP
A2: COMPAÑÍA: | B2: HEG DISEÑO E INSTALACION SA DE CV
A3: CONCEPTO: | B3: FACTURAS PENDIENTES DE COBRO DEL PROYECTO PARALLEL HOP
A4: FECHA: | B4: 30 DE ABRIL DEL 2025
B6: CONCEPTO | D6: IMPORTE
B7: CONTRATADO A LA FECHA | D7: 317799.33
B8: COBRADO | D8: 188090.13
B9: POR COBRAR | D9: =+D7-D8 -> 129709.2
B10: FONDO DE GARANTIA | D10: 0
B11: LQUIDO POR COBRAR | D11: =+D9-D10 -> 129709.2
A13: N° | B13: FECHA | C13: N° FACTURA | D13: CONCEPTO | E13: IMPORTE A COBRAR | F13: IMPORTE COBRADO | G13: SALDO POR COBRAR | H13: FECHA DE PAGO
E15: =SUM(E14) -> 0 | F15: =SUM(F14) -> 0 | G15: =SUM(G14) -> 0

Sheet PUERTA POLANCO
A2: COMPAÑÍA: | B2: HEG DISEÑO E INSTALACION SA DE CV
A3: CONCEPTO: | B3: FACTURAS PENDIENTES DE COBRO DEL PROYECTO PUERTA POLANCO
A4: FECHA: | B4: 29 DE AGOSTO DEL 2025
B6: CONCEPTO | D6: IMPORTE
B7: CONTRATADO A LA FECHA | D7: 198456.23
B8: COBRADO | D8: =66655.68+78476.02 -> 145131.7
B9: POR COBRAR | D9: =+D7-D8 -> 53324.534
B10: FONDO DE GARANTIA | D10: 0
B11: LQUIDO POR COBRAR | D11: =+D9-D10 -> 53324.534
A13: N° | B13: FECHA | C13: N° FACTURA | D13: CONCEPTO | E13: IMPORTE A COBRAR | F13: IMPORTE COBRADO | G13: SALDO POR COBRAR | H13: FECHA DE PAGO
E15: =SUM(E14) -> 0 | F15: =SUM(F14) -> 0 | G15: =SUM(G14) -> 0

Sheet REFORMA 445
A2: COMPAÑÍA: | B2: HEG DISEÑO E INSTALACION SA DE CV
A3: CONCEPTO: | B3: FACTURAS PENDIENTES DE COBRO DEL PROYECTO REFORMA 445
A4: FECHA: | B4: 06 DE OCTUBRE DEL 2025
B6: CONCEPTO | D6: IMPORTE
B7: CONTRATADO A LA FECHA | D7: =126412000+7192000 -> 133604000
B8: COBRADO | D8: 94590000
B9: POR COBRAR | D9: =+D7-D8 -> 39014000
B10: FONDO DE GARANTIA | D10: 0
B11: LQUIDO POR COBRAR | D11: =+D9-D10 -> 39014000
A13: N° | B13: FECHA | C13: N° FACTURA | D13: CONCEPTO | E13: IMPORTE A COBRAR | F13: IMPORTE COBRADO | G13: SALDO POR COBRAR | H13: FECHA DE PAGO
E15: =+E14 -> 0 | F15: =+F14 -> 0 | G15: =+G14 -> 0

Sheet ST REGIS 
A2: COMPAÑÍA: | B2: HEG DISEÑO E INSTALACION SA DE CV
A3: CONCEPTO: | B3: FACTURAS PENDIENTES DE COBRO DEL PROYECTO ST REGIS
A4: FECHA: | B4: 02 DE AGOSTO DEL 2024
B6: CONCEPTO | D6: IMPORTE
B7: CONTRATADO A LA FECHA | D7: 86969393
B8: COBRADO | D8: 81568963
B9: POR COBRAR | D9: =+D7-D8 -> 5400429.3
B10: FONDO DE GARANTIA 5% | D10: =+D7*5% -> 4348469.6
B11: LQUIDO POR COBRAR | D11: =+D9-D10 -> 1051959.7
A13: N° | B13: FECHA | C13: N° FACTURA | D13: CONCEPTO | E13: IMPORTE A COBRAR | F13: IMPORTE COBRADO | G13: SALDO POR COBRAR | H13: FECHA DE PAGO

Sheet ST REGIS PINTURA

Sheet TAXCO CUERNAVACA
A2: COMPAÑÍA: | B2: HEG DISEÑO E INSTALACION SA DE CV
A3: CONCEPTO: | B3: RECIBOS PENDIENTES DE COBRO DEL PROYECTO TAXCO CUERNAVACA
A4: FECHA: | B4: 22 DE ENERO DEL 2025
B6: CONCEPTO | D6: IMPORTE
B7: CONTRATADO A LA FECHA | D7: 763066.39
B8: COBRADO | D8: 400000
B9: POR COBRAR | D9: =+D7-D8 -> 363066.39
B10: FONDO DE GARANTIA | D10: 0
B11: LQUIDO POR COBRAR | D11: =+D9-D10 -> 363066.39
A13: N° | B13: FECHA | C13: N° FACTURA | D13: CONCEPTO | E13: IMPORTE A COBRAR | F13: IMPORTE COBRADO | G13: SALDO POR COBRAR | H13: FECHA DE PAGO
E15: =+E14 -> 0 | F15: =+F14 -> 0 | G15: =+G14 -> 0

Sheet TORRE BOSQUES
A2: COMPAÑÍA: | B2: HEG DISEÑO E INSTALACION SA DE CV
A3: CONCEPTO: | B3: RECIBOS PENDIENTES DE COBRO DEL PROYECTO TORRE BOSQUES
A4: FECHA: | B4: 29 DE AGOSTO DEL 2025
B6: CONCEPTO | D6: IMPORTE
B7: CONTRATADO A LA FECHA | D7: =231557.12*1.16 -> 268606.26
B8: COBRADO | D8: 188024.38
B9: POR COBRAR | D9: =+D7-D8 -> 80581.879
B10: FONDO DE GARANTIA | D10: 0
B11: LQUIDO POR COBRAR | D11: =+D9-D10 -> 80581.879
A13: N° | B13: FECHA | C13: N° FACTURA | D13: CONCEPTO | E13: IMPORTE A COBRAR | F13: IMPORTE COBRADO | G13: SALDO POR COBRAR | H13: FECHA DE PAGO
E15: =+E14 -> 0 | F15: =+F14 -> 0 | G15: =+G14 -> 0

Sheet T CHAPULTEPEC
A2: COMPAÑÍA: | B2: HEG DISEÑO E INSTALACION SA DE CV
A3: CONCEPTO: | B3: RECIBOS PENDIENTES DE COBRO DEL PROYECTO TORRE CHAPULTEPEC
A4: FECHA: | B4: 29 DE AGOSTO DEL 2025
B6: CONCEPTO | D6: IMPORTE
B7: CONTRATADO A LA FECHA | D7: =47091.36+17798.1 -> 64889.46
B8: COBRADO | D8: =47091.36+17799.1 -> 64890.46
B9: POR COBRAR | D9: =+D7-D8 -> -1
B10: FONDO DE GARANTIA | D10: 0
B11: LQUIDO POR COBRAR | D11: =+D9-D10 -> -1
A13: N° | B13: FECHA | C13: N° FACTURA | D13: CONCEPTO | E13: IMPORTE A COBRAR | F13: IMPORTE COBRADO | G13: SALDO POR COBRAR | H13: FECHA DE PAGO
E15: =+E14 -> 0 | F15: =+F14 -> 0 | G15: =+G14 -> 0

Sheet T REFORMA MTTO
A2: COMPAÑÍA: | B2: HEG DISEÑO E INSTALACION SA DE CV
A3: CONCEPTO: | B3: FACTURAS PENDIENTES DE COBRO DEL PROYECTO TORRE REFORMA MANTENIMIENTO
A4: FECHA: | B4: 25 DE AGOSTO DEL 2025
B6: CONCEPTO | D6: IMPORTE
B7: CONTRATADO A LA FECHA | D7: 12166.54
B8: COBRADO | D8: 0
B9: POR COBRAR | D9: =+D7-D8 -> 12166.54
B10: FONDO DE GARANTIA
B11: LQUIDO POR COBRAR | D11: =+D9-D10 -> 12166.54
A13: N° | B13: FECHA | C13: N° FACTURA | D13: CONCEPTO | E13: IMPORTE A COBRAR | F13: IMPORTE COBRADO | G13: SALDO POR COBRAR | H13: FECHA DE PAGO
A14: 1 | B14: 45882 | C14: 4266 | D14: SUMINISTRO Y COLOCACION DE CRISTAL DAÑADO | E14: 12166.54 | F14: 0 | G14: 12166.54
E15: =+E14 -> 12166.54 | F15: =+F14 -> 0 | G15: =+G14 -> 12166.54

Sheet T VIRREYES AUDITORIO
A2: COMPAÑÍA: | B2: HEG DISEÑO E INSTALACION SA DE CV
A3: CONCEPTO: | B3: FACTURAS PENDIENTES DE COBRO DEL PROYECTO TORRE VIRREYES 2023
A4: FECHA: | B4: 13 DE OCTUBRE DEL 2025
B6: CONCEPTO | D6: IMPORTE
B7: CONTRATADO A LA FECHA | D7: 3384631.8
B8: COBRADO | D8: =3046168.58+338463.18 -> 3384631.8
B9: POR COBRAR | D9: =+D7-D8 -> 0.046399999
B10: FONDO DE GARANTIA 10% | D10: =291778.6*1.16 -> 338463.18
B11: LQUIDO POR COBRAR | D11: =+D9-D10 -> -338463.13
A13: N° | B13: FECHA | C13: N° FACTURA | D13: CONCEPTO | E13: IMPORTE A COBRAR | F13: IMPORTE COBRADO | G13: SALDO POR COBRAR | H13: FECHA DE PAGO
E15: =+E14 -> 0 | F15: =+F14 -> 0 | G15: =+G14 -> 0

Sheet VTLUX
A2: COMPAÑÍA: | B2: HEG DISEÑO E INSTALACION SA DE CV
A3: CONCEPTO: | B3: FACTURAS PENDIENTES DE COBRO DEL PROYECTO VIDALTA TORRE LUX
A4: FECHA: | B4: 04 DE MARZO DEL 2024
B6: CONCEPTO | D6: IMPORTE
B7: CONTRATADO A LA FECHA | D7: 1.3011247e+08
B8: COBRADO | D8: 1.2970971e+08
B9: POR COBRAR | D9: =+D7-D8 -> 402753.62
B10: FONDO DE GARANTIA | D10: 0
B11: LQUIDO POR COBRAR | D11: =+D9-D10 -> 402753.62
A13: N° | B13: FECHA | C13: N° FACTURA | D13: CONCEPTO | E13: IMPORTE A COBRAR | F13: IMPORTE COBRADO | G13: SALDO POR COBRAR | H13: FECHA DE PAGO

Sheet VIDALTA 2803
A2: COMPAÑÍA: | B2: HEG DISEÑO E INSTALACION SA DE CV
A3: CONCEPTO: | B3: FACTURAS PENDIENTES DE COBRO DEL PROYECTO VIDALTA TORRE LUX
A4: FECHA: | B4: 10 DE OCTUBRE DEL 2025
B6: CONCEPTO | D6: IMPORTE
B7: CONTRATADO A LA FECHA | D7: 470854.29
B8: COBRADO | D8: 356055
B9: POR COBRAR | D9: =+D7-D8 -> 114799.29
B10: FONDO DE GARANTIA | D10: 0
B11: LQUIDO POR COBRAR | D11: =+D9-D10 -> 114799.29
A13: N° | B13: FECHA | C13: N° FACTURA | D13: CONCEPTO | E13: IMPORTE A COBRAR | F13: IMPORTE COBRADO | G13: SALDO POR COBRAR | H13: FECHA DE PAGO

Sheet VILLAS KANAI
A2: COMPAÑÍA: | B2: HEG DISEÑO E INSTALACION SA DE CV
A3: CONCEPTO: | B3: FACTURAS PENDIENTES DE COBRO DEL PROYECTO VILLAS KANAI
A4: FECHA: | B4: 08 DE ABRIL DEL 2025
B6: CONCEPTO | D6: IMPORTE
B7: CONTRATADO A LA FECHA | D7: 5257120
B8: COBRADO | D8: 4494611.2
B9: POR COBRAR | D9: =+D7-D8 -> 762508.76
B10: FONDO DE GARANTIA 5% | D10: =+D7*5% -> 262856
B11: LQUIDO POR COBRAR | D11: =+D9-D10 -> 499652.76
A13: N° | B13: FECHA | C13: N° FACTURA | D13: CONCEPTO | E13: IMPORTE A COBRAR | F13: IMPORTE COBRADO | G13: SALDO POR COBRAR | H13: FECHA DE PAGO
E15: =SUM(E14) -> 0 | F15: =SUM(F14) -> 0 | G15: =SUM(G14) -> 0

Sheet VILLAS KANAI 2025
A2: COMPAÑÍA: | B2: HEG DISEÑO E INSTALACION SA DE CV
A3: CONCEPTO: | B3: FACTURAS PENDIENTES DE COBRO DEL PROYECTO VILLAS KANAI 2025
A4: FECHA: | B4: 28 DE JULIO DEL 2025
B6: CONCEPTO | D6: IMPORTE
B7: CONTRATADO A LA FECHA | D7: 1552384.5
B8: COBRADO | D8: =1315485.05+111204.85 -> 1426689.9
B9: POR COBRAR | D9: =+D7-D8 -> 125694.65
A12: N° | B12: FECHA | C12: N° FACTURA | D12: CONCEPTO | E12: IMPORTE A COBRAR | F12: IMPORTE COBRADO | G12: SALDO POR COBRAR | H12: FECHA DE PAGO
E14: =+E13 -> 0 | F14: =+F13 -> 0 | G14: =+G13 -> 0

Sheet VOLCAN 150
A2: COMPAÑÍA: | B2: HEG DISEÑO E INSTALACION SA DE CV
A3: CONCEPTO: | B3: FACTURAS PENDIENTES DE COBRO DEL PROYECTO VOLCAN 150 2024
A4: FECHA: | B4: 15 DE OCTUBRE DEL 2025
B6: CONCEPTO | D6: IMPORTE
B7: CONTRATADO A LA FECHA | D7: 116534.32
B8: COBRADO | D8: 98605.46
B9: POR COBRAR | D9: =+D7-D8 -> 17928.859
A12: N° | B12: FECHA | C12: N° FACTURA | D12: CONCEPTO | E12: IMPORTE A COBRAR | F12: IMPORTE COBRADO | G12: SALDO POR COBRAR | H12: FECHA DE PAGO
E14: =SUM(E13) -> 0 | F14: =SUM(F13) -> 0 | G14: =SUM(G13) -> 0

Sheet WESTIN GDL 
A2: COMPAÑÍA: | B2: HEG DISEÑO E INSTALACION SA DE CV
A3: CONCEPTO: | B3: FACTURAS PENDIENTES DE COBRO DEL PROYECTO WESTIN GUADALAJARA
A4: FECHA: | B4: 20 DE MAYO DEL 2025
B6: CONCEPTO | D6: IMPORTE
B7: CONTRATADO A LA FECHA | D7: 435812
B8: COBRADO | D8: 305068.4
B9: POR COBRAR | D9: =+D7-D8 -> 130743.6
A12: N° | B12: FECHA | C12: N° FACTURA | D12: CONCEPTO | E12: IMPORTE A COBRAR | F12: IMPORTE COBRADO | G12: SALDO POR COBRAR | H12: FECHA DE PAGO
A13: 1 | B13: 45793 | C13: 4157 | D13: ULTIMO PAGO | E13: 130743.6 | F13: 0 | G13: 130743.6
E14: =SUM(E13) -> 130743.6 | F14: =SUM(F13) -> 0 | G14: =SUM(G13) -> 130743.6
