Workbook

Sheet Hoja1
H3: 20 DE FEBRERO DEL 2023
B9: PROYECTO: | C9: TORRE PARALLEL | H9: PEDIDO #335
B10: DIRECCIÓN: | C10: VISTA REAL MZ III Lt. 14, COL. GREEN HOUSE
C11: SEGUNDA ETAPA HUIXQUILUCAN, EDO. DE MÉXICO.
B15: ATN: DANIEL RUIZ; HUMBERTO JIMENEZ | H15: GIOVANNI
B17: # | C17: CONCEPTO | F17: UNIDAD | G17: PEDIDO | H17: OBSERVACIONES
B19: 1 | C19: SERVICIO A IMPRESORA EN OBRA | F19: LOTE | G19: 1
B23: FORMULÓ:
B25: ARQ. JONHATAN ALEJANDRO CANO MUNIVE

Sheet RESPALDO
E2: Cd. De México a 06 de Noviembre del 2025
E4: PROVEEDOR: | F4: JUAN ALEJANDRO CHAVEZ
F5: AV. NELLIE CAMPOBELLO No.. 129 EDIF. CORA DEPTO 604
F6: COL. CAROLA
F7: DELG. ALVARO OBREGON
E10: ATENCION: | F10: ALEJANDRO CHAVEZ
B11: HEG DISEÑO E INSTALACION, S.A. DE C.V.
B13: PEDIDO: | C13: 250
B14: FAMILIA: | C14: EM | E14: PROYECTO: | F14: 00443 JAIME NUNO
B15: CONCEPTO: | C15: EMPAQUES | E15: CLAN: | F15: MATERIALES
E16: ENTREGAR EN: | F16: JAIME NUNO
F17: INSURGENTES SUR 1921
F18: Col. GUADALUPE INN
F19: DEL. ALVARO OBREGON
F20: CP 01020
B23: NO. | C23: DESCRIPCION | D23: UNIDAD | E23: MEDIDA | G23: CANTIDAD | H23: P. UNITARIO | I23: IMPORTE | J23: CLAVE | K23: DIBUJO | L23: M.L. | M23: ACABADO | N23: KG | O23: PRECIOxKG
B24: 1 | C24: EMPAQUE DE SANTOPRENO HONGO MEDIANO | D24: ROLLO DE 100 MTS. | G24: 3 | H24: 780 | I24: =H24*G24 -> 2340 | L24: 300 | M24: COLOR NEGRO | N24: 18 | O24: =I24/N24 -> 130
B25: 2 | C25: EMPAQUE DE SANTOPRENO RESPALDO CRISTAL | D25: ROLLO DE 100 MTS. | G25: 1 | H25: 585 | I25: =H25*G25 -> 585 | L25: 100 | M25: COLOR NEGRO | N25: 4.5 | O25: =I25/N25 -> 130
B26: 3 | C26: EMPAQUE DE SANTOPRENO MEDIA LUNA CHICA | D26: ROLLO DE 100 MTS. | G26: 2.5 | H26: 390 | I26: =H26*G26 -> 975 | L26: 250 | M26: COLOR NEGRO | N26: 7.5 | O26: =I26/N26 -> 130
B27: 4 | C27: FELPA DE 7 X 5 CON PELO INTERMEDIO | D27: ROLLO DE 100 MTS. | G27: 1 | H27: 3 | I27: 300 | L27: 100 | M27: COLOR NEGRO | N27: 0 | O27: =I27/N27 -> #DIV/0!
B28: 5 | I28: =H28*G28 -> 0
B29: 6 | I29: =H29*G29 -> 0
B30: 7 | I30: =H30*G30 -> 0
B31: 8 | I31: =H31*G31 -> 0
B32: 9 | I32: =H32*G32 -> 0
B33: 10 | I33: =H33*G33 -> 0
B34: 11 | I34: =H34*G34 -> 0
B35: 12 | I35: =H35*G35 -> 0
B36: 13 | I36: =H36*G36 -> 0
B37: 14 | I37: =H37*G37 -> 0
H39: IMPORTE | I39: =SUM(I24:I37) -> 4200
C40: PAGOS INMEDIATOS | H40: DESCUENTO | L40: -
C41: APROBADO | H41: SUBTOTAL | I41: =+I39-I40 -> 4200 | L41: SITUACIONES ESPECIALES
C42: 06/11/2025 | H42: IVA | I42: =+I41*0.16 -> 672
C43: FECHA DE APROBACION | H43: TOTAL | I43: =+I41+I42 -> 4872
C45: FORMULÓ
C46: D. ERICK RUIZ

Sheet CATALOGO
A1: DESCRIPCION | B1: CLAVE | C1: P. UNITARIO | D1: MONEDA
A2: 94 PRIMER 3M SCOTCH-WELD PROMOTOR DE ADHESIÓN PARA UNA GRAN VARIEDAD DE SUSTRATOS, 0.946 L , CLARO
A3: ABRAZADERA SIN FIN
A4: ABRAZADERA SNAPLOCK
A5: ABRAZADERA SOLERA 48 mm. BROCHE [ACCAS48BRO]
A6: ABRAZADERA SOLERA 60 mm. BROCHE [ACCAS60BRO]
A7: ABRAZADERA TORNILLO DE 48 MM [ACCAT48]
A8: ABRAZADERA TORNILLO DE 60 MM [ACCAT60]
A9: ACEITE PARA CORTE ALUMINIO
A10: ADAPTACION DE RIELES PARA TALADRO MULTIPLE FELDER FD21 CON NIVELADORES RODAJA
A11: ADAPTACION DE RIELES SIERRAS DE DISCO
A12: ADAPTADOR IMPACTO 1/4" A 1/2"
A13: ADHESIVO ESTRUCTURAL SIKASIL SG 18 NEGRO MATE
... A1017: ZOCLO CABEZAL S70
A1018: 30M LD030P MAKITA | B1018: 3909 | C1018: 1838 | D1018: MXP
A1019: ACRILASTIC SELLADOR ACRÍLICO - BEIGE | B1019: ROD-25 | C1019: 46 | D1019: MXP
A1020: ACRILASTIC SELLADOR ACRÍLICO - BLANCO | B1020: ROD-23 | C1020: 46 | D1020: MXP
A1021: ACRILASTIC SELLADOR ACRÍLICO - GRIS | B1021: ROD-26 | C1021: 46 | D1021: MXP
A1022: ACRILASTIC SELLADOR ACRÍLICO - NEGRO | B1022: ROD-24 | C1022: 46 | D1022: MXP
A1023: ACRILICO MEDIA LUNA PARA RETENER AGUA EN PISO, DE 12X6MM L=2.5MTS CON CINTA ADHESIVA | B1023: 01170121 | C1023: =145.6*0.8*0.95 -> 110.656 | D1023: MXP
A1024: ALCOHOL ISOPROPILICO | B1024: ROD-46 | C1024: 60 | D1024: MXP
A1025: ALETA LARGA 135 P/ CRISTAL 10MM L=2.5 METROS | B1025: 01170105 | C1025: =51.45*0.8*0.95 -> 39.102 | D1025: MXP
A1026: ANCLA BASE PARA MARQUESINA ACERO INOX 304 | B1026: 14010101 | C1026: =556.5*0.8*0.95 -> 422.94 | D1026: MXP
A1027: ANCLA DOBLE MURO CRISTAL PARA MARQUESINA ACERO INOX 304 | B1027: 14010501 | C1027: =2369.5*0.8*0.95 -> 1800.82 | D1027: MXP
A1028: ANCLA SIMPLE MURO CRISTAL PARA MARQUESINA ACERO INOX 304 | B1028: 14010401 | C1028: =1256.5*0.8*0.95 -> 954.94 | D1028: MXP
A1029: ANGULO C-C 90° INOVA, NÍQUEL SATINADO | B1029: 01030202 | C1029: =573.99*0.8*0.95 -> 436.2324 | D1029: MXP
A1030: ANGULO C-C 90° INOVA,CROMO BRILLANTE | B1030: 01030201 | C1030: =558.94*0.8*0.95 -> 424.7944 | D1030: MXP
A1031: ANGULO C-C AQUA LIGHT 90°, CROMO BRILLANTE | B1031: 01070201 | C1031: =404.49*0.8*0.95 -> 307.4124 | D1031: MXP
A1032: ANGULO C-C AQUA LIGHT 90°, NÍQUEL SATINADO | B1032: 01070202 | C1032: =416.43*0.8*0.95 -> 316.4868 | D1032: MXP
A1033: ANGULO DE ALUMINIO 1/4" DE 3"X2"X200MM C/2 BARRENOS ANODIZADO NATURAL MATE | B1033: 13110401 | C1033: =220.85*0.8*0.95 -> 167.846 | D1033: MXP
A1034: ANGULO DE ALUMINIO 1/4" DE 3"X2"X250MM C/2 BARRENOS ANODIZADO NATURAL MATE | B1034: 13110402 | C1034: =244.63*0.8*0.95 -> 185.9188 | D1034: MXP
A1035: ANGULO DE ALUMINIO 1/4" DE 3"X2"X300MM C/3 BARRENOS ANODIZADO NATURAL MATE | B1035: 13110403 | C1035: =299.09*0.8*0.95 -> 227.3084 | D1035: MXP
A1036: ANGULO DE ALUMINIO 1/4" DE 3"X2"X350MM C/3 BARRENOS ANODIZADO NATURAL MATE | B1036: 13110404 | C1036: =331.4*0.8*0.95 -> 251.864 | D1036: MXP
A1037: ANGULO DE ALUMINIO 1/4" DE 3"X2"X400MM C/3 BARRENOS ANODIZADO NATURAL MATE | B1037: 13110405 | C1037: =394.86*0.8*0.95 -> 300.0936 | D1037: MXP
A1038: ANGULO INOVA C/C EN T CROMO BRILLANTE | B1038: 01030401 | C1038: =805.8*0.8*0.95 -> 612.408 | D1038: MXP
A1039: ANGULO INOVA C-C EN T NIQ SATINADO | B1039: 01030402 | C1039: =824.25*0.8*0.95 -> 626.43 | D1039: MXP
A1040: ANGULO INOVA M/C EN T CROMO BRILLANTE | B1040: 01030301 | C1040: =475.57*0.8*0.95 -> 361.4332 | D1040: MXP
A1041: ANGULO INOVA M/C EN T NIQ SATINADO | B1041: 01030302 | C1041: =488.35*0.8*0.95 -> 371.146 | D1041: MXP
A1042: ANGULO M-C 90° INOVA,CROMO BRILLANTE | B1042: 01030101 | C1042: =429.67*0.8*0.95 -> 326.5492 | D1042: MXP
A1043: ANGULO M-C 90° INOVA,NIQUEL SATINADO | B1043: 01030102 | C1043: =462.75*0.8*0.95 -> 351.69 | D1043: MXP
A1044: ANGULO M-C AQUA LIGHT 90°, CROMO BRILLANTE | B1044: 01070101 | C1044: =318.04*0.8*0.95 -> 241.7104 | D1044: MXP
A1045: ANGULO M-C AQUA LIGHT 90°, NÍQUEL SATINADO | B1045: 01070102 | C1045: =328.4*0.8*0.95 -> 249.584 | D1045: MXP
A1046: ARAÑA 1 BRAZO 220 AC. INOX. 316 BRILLANTE | B1046: 13020101 | C1046: =341.25*0.8*0.95 -> 259.35 | D1046: MXP
A1047: ARAÑA 1 BRAZO 220, AC. INOX 304 SATINADO | B1047: 13010102 | C1047: =243.6*0.8*0.95 -> 185.136 | D1047: MXP
A1048: ARAÑA 2 BRAZOS 180° 220 AC. INOX 316 BRILLANTE | B1048: 13020201 | C1048: =404.95*0.8*0.95 -> 307.762 | D1048: MXP
A1049: ARAÑA 2 BRAZOS 180° 220 AC. INOX.304 SATINADO | B1049: 13010202 | C1049: =300.3*0.8*0.95 -> 228.228 | D1049: MXP
A1050: ARAÑA 2 BRAZOS 220 AC. INOX. 304 SATINADO | B1050: 13010302 | C1050: =354.9*0.8*0.95 -> 269.724 | D1050: MXP
A1051: ARAÑA 2 BRAZOS 220 AC. INOX. 316 BRILLANTE | B1051: 13020301 | C1051: =482.3*0.8*0.95 -> 366.548 | D1051: MXP
A1052: ARAÑA 3 BRAZOS 220 AC. INOX 304 SATINADO | B1052: 13010402 | C1052: =477.75*0.8*0.95 -> 363.09 | D1052: MXP
A1053: ARAÑA 3 BRAZOS 220 AC. INOX. 316 BRILLANTE | B1053: 13020401 | C1053: =641.55*0.8*0.95 -> 487.578 | D1053: MXP
A1054: ARAÑA 4 BRAZOS 220 AC. INOX. 316 BRILLANTE | B1054: 13020501 | C1054: =814.45*0.8*0.95 -> 618.982 | D1054: MXP
A1055: ARAÑA 4 BRAZOS 220 AC. INOX.304 SATINADO | B1055: 13010502 | C1055: =596.05*0.8*0.95 -> 452.998 | D1055: MXP
A1056: ARAÑA COSTI-PLAC.1 BZO. CENTRADA AC. INOX .304 SATINADO | B1056: 13050102 | C1056: =209.3*0.8*0.95 -> 159.068 | D1056: MXP
A1057: ARAÑA COSTI-PLACA 1 BRAZO DER. AC.INOX. 304 SATINADO | B1057: 13050302 | C1057: =312.73*0.8*0.95 -> 237.6748 | D1057: MXP
A1058: ARAÑA COSTI-PLACA 1 BRAZO IZQ. AC.INOX. 304 SATINADO | B1058: 13050202 | C1058: =312.73*0.8*0.95 -> 237.6748 | D1058: MXP
A1059: ARAÑA COSTI-PLACA 2BRAZOS1 IZQUIERDA AC. INOX. 316 BRILLANTE | B1059: 13060501 | C1059: =515.9*0.8*0.95 -> 392.084 | D1059: MXP
A1060: ARAÑA COST-PLACA 1 BRAZO DER. AC INOX 316 BRILLANTE | B1060: 13060201 | C1060: =371*0.8*0.95 -> 281.96 | D1060: MXP
A1061: ARAÑA COST-PLACA 1 BRAZO IZQ. AC INOX 316 BRILLANTE | B1061: 13060301 | C1061: =371*0.8*0.95 -> 281.96 | D1061: MXP
A1062: ARAÑA COST-PLACA 1BRAZO CENTRADA AC .INOX. 316 BRILLANTE | B1062: 13060101 | C1062: =276.5*0.8*0.95 -> 210.14 | D1062: MXP
A1063: ARAÑA COST-PLACA 2BRAZOS1 IZQUIERDA AC. INOX. 304 SATINADO | B1063: 13050402 | C1063: =381.15*0.8*0.95 -> 289.674 | D1063: MXP
A1064: ARAÑA COST-PLACA 2BRAZOS2 DERECHA AC. INOX. 316 BRILLANTE | B1064: 13060401 | C1064: =515.9*0.8*0.95 -> 392.084 | D1064: MXP
A1065: ARAÑA COST-PLACA 2BRAZOS2 DERECHA, AC. INOX. 304 SATINADO | B1065: 13050502 | C1065: =381.15*0.8*0.95 -> 289.674 | D1065: MXP
A1066: ASPIRADORA MAKITA 1100W 20L VC2 000L | B1066: 4409 | C1066: 3836 | D1066: MXP
A1067: ASPIRADORA MAKITA 12V 106FDZ CL1 08FDZ | B1067: 4990 | C1067: 960 | D1067: MXP
A1068: ASPIRADORA MAKITA 18V DCL 180RFB | B1068: 5121 | C1068: 3044 | D1068: MXP
A1069: ASPIRADORA MAKITA 18V VC7 50LSX3 | B1069: 5120 | C1069: 4599 | D1069: MXP
A1070: ASPIRADORA MAKITA 40V L00 3GA103 | B1070: 4446 | C1070: 4941 | D1070: MXP
A1071: ASPIRADORA MAKITA T MOCHILA 18 VC2 61ZX11 | B1071: 4514 | C1071: 5723 | D1071: MXP
A1072: ATORNILLADOR BOSCH 12V 19F40G GSR 1000SM | B1072: 3160 | C1072: 1276 | D1072: MXP
A1073: ATORNILLADOR BOSCH 12V VV 19G80GGSR 120LI | B1073: 2565 | C1073: 1978 | D1073: MXP
A1074: ATORNILLADOR BOSCH 3,6V 19H21 BOS CHGO2 | B1074: 2634 | C1074: 590 | D1074: MXP
A1075: ATORNILLADOR BOSCH 5EN1 19F60G SR1 2V15FC | B1075: 2633 | C1075: 4610 | D1075: MXP
A1076: ATORNILLADOR BOSCH 700W VV 14451GSR 645TE | B1076: 2637 | C1076: 3228 | D1076: MXP
A1077: ATORNILLADOR DEWALT 20V IMPAC DCF 887D2 | B1077: 3309 | C1077: 4652 | D1077: MXP
... A1105: ATORNILLADOR MILWAUKEE M18 TABLAROCA 286622 | B1105: 4113 | C1105: 9149 | D1105: MXP
A1106: BACKER ROD CILÍNDRICO - 1 " CAJA CON 182 ML | B1106: ROD-31 | C1106: 1732 | D1106: MXP
A1107: BACKER ROD CILÍNDRICO - 1/2" CAJA CON 762 ML | B1107: ROD-29 | C1107: 2050 | D1107: MXP
A1108: BACKER ROD CILÍNDRICO - 1/4" CAJA 1,219 ML | B1108: ROD-27 | C1108: 1680 | D1108: MXP
A1109: BACKER ROD CILÍNDRICO - 3/4" CAJA CON 335 ML | B1109: ROD-30 | C1109: 1815 | D1109: MXP
A1110: BACKER ROD CILÍNDRICO - 3/8" CAJA CON 640 ML | B1110: ROD-28 | C1110: 1215 | D1110: MXP
A1111: BACKER ROD PLANO GRIS - 10 MM X 20 MM | B1111: ROD-32 | C1111: 4.1 | D1111: MXP
A1112: BARANDAL TIPO ELÍPTICO SIMPLE AC. INOXIDABLE 304 | B1112: 10090102 | C1112: =1185.8*0.8*0.95 -> 901.208 | D1112: MXP
A1113: BARANDAL TIPO ELÍPTICO, ACERO INOXIDABLE 304 | B1113: 10090101 | C1113: =1462.83*0.8*0.95 -> 1111.7508 | D1113: MXP
A1114: BARANDAL TIPO POSTE REDONDO DE 2" CON 4 CONECTORES A 90° ACERO INOXIDABLE | B1114: 10090404 | C1114: =1618.43*0.8*0.95 -> 1230.0068 | D1114: MXP
A1115: BARANDAL TIPO POSTE REDONDO DE L= 1.05MTS, DE 2" ACERO INOXIDABLE | B1115: 10090403 | C1115: =838.21*0.8*0.95 -> 637.0396 | D1115: MXP
A1116: BARANDAL TIPO POSTE REDONDO DE L= 1.05MTS, DE 2" CON 2 CONECTORES FORTE ACERO INOXIDABLE | B1116: 10090402 | C1116: =1228.32*0.8*0.95 -> 933.5232 | D1116: MXP
A1117: BARANDAL TIPO POSTE REDONDO DE L= 1.05MTS, DE 2" CON 4 CONECTORES FORTE ACERO INOXIDABLE | B1117: 10090401 | C1117: =1618.43*0.8*0.95 -> 1230.0068 | D1117: MXP
A1118: BARANDAL TIPO POSTE TRIANGULAR ACERO INOXIDABLE 304 | B1118: 10090301 | C1118: =948.15*0.8*0.95 -> 720.594 | D1118: MXP
A1119: BARANDAL TIPO POSTE PARA BARRA 12MM ACERO INOX. 304 | B1119: 10090501 | C1119: =1743*0.8*0.95 -> 1324.68 | D1119: MXP
A1120: BARANDAL TIPO POSTE REDONDO DE L=1.05MTS DE 2" ACERO INOX, C/2 CONECTORES MEDIA LUNA ZAMAK | B1120: 10090702 | C1120: =954.35*0.8*0.95 -> 725.306 | D1120: MXP
A1121: BARANDAL TIPO POSTE REDONDO DE L=1.05MTS DE 2" ACERO INOX, C/4 CONECTORES MEDIA LUNA ZAMAK | B1121: 10090701 | C1121: =1070.5*0.8*0.95 -> 813.58 | D1121: MXP
A1122: BARANDAL TIPO POSTE TRIANGULAR SIMPLE ACERO INOX. 304 | B1122: 10090302 | C1122: =788.55*0.8*0.95 -> 599.298 | D1122: MXP
A1123: BARANDAL TIPO SOLERA ACERO INOXIDABLE 304 | B1123: 10090201 | C1123: =1459.5*0.8*0.95 -> 1109.22 | D1123: MXP
A1124: BARANDAL TIPO SOLERA SIMPLE ACERO INOXIDABLE 304 | B1124: 10090202 | C1124: =1293.6*0.8*0.95 -> 983.136 | D1124: MXP
A1125: BARRA CENTRAL DIAM 2", L=500MM, ACERO INOX. 304 | B1125: 13120301 | C1125: =2058.02*0.8*0.95 -> 1564.0952 | D1125: MXP
A1126: BARRA CENTRAL DIAM 2", L=700MM, ACERO INOX. 304 | B1126: 13120302 | C1126: =2365.37*0.8*0.95 -> 1797.6812 | D1126: MXP
A1127: BARRA ESTABILIZADORA M/C 800/1000MM AC. IN BRILLANTE | B1127: 01160101 | C1127: =587.73*0.8*0.95 -> 446.6748 | D1127: MXP
A1128: BARRA ESTABILIZADORA C-C 800/1000MM AJUS AC. INOX. SAT. | B1128: 01160202 | C1128: =574.37*0.8*0.95 -> 436.5212 | D1128: MXP
A1129: BARRA ESTABILIZADORA C-C 800/1000MM AJUS.BRILLANTE | B1129: 01160201 | C1129: =574.37*0.8*0.95 -> 436.5212 | D1129: MXP
A1130: BARRA ESTABILIZADORA M-C 800/1000MM AC.INOX. SATINADO | B1130: 01160102 | C1130: =587.73*0.8*0.95 -> 446.6748 | D1130: MXP
...

Sheet Sheet1
B7: CLAVE | C7: CONCEPTO | D7: PRECIO | E7: MONEDA
C8: Silicón Uso General 100% Grado Arq. - Transparente | D8: 76 | F8: Transp.
C9: Silicón Uso General 100% Grado Arq. - Blanco | D9: 76 | F9: Blanco
C10: Silicón Uso General 100% Grado Arq. - Negro | D10: 76 | F10: Negro
C11: Silicón Anti-Hongos - Transparente | D11: 76 | F11: Transparente
C12: Silicón Anti-Hongos - Blanco | D12: 76 | F12: Blanco
C13: Sikasil N-Plus - Transparente | D13: 112 | F13: Transparente
C14: Sikasil N-Plus - Blanco | D14: 112 | F14: Blanco
C15: Sikasil N-Plus - Gris | D15: 112 | F15: Gris
C16: Sikasil N-Plus - Negro | D16: 112 | F16: Negro
C17: Sikasil WS-305 Sellador Estructural - Negro | D17: 168 | F17: Negro
C18: Sikasil WS-305 Sellador Estructural - Blanco | D18: 168 | F18: Blanco
C19: Sikasil WS-305 Sellador Estructural - Gris | D19: 168 | F19: Gris
... C22: U-Seal 907 Poliuretano - Negro | D22: 82 | F22: Gris
C23: U-Seal 907 Poliuretano - Gris | D23: 82
C24: Simp Seal 25 Sellador Hibrido - Blanco | D24: 92 | F24: Blanco, Negro
C25: Simp Seal 25 Sellador Hibrido - Negro | D25: 92 | F25: Gris claro
C26: Simp Seal 25 Sellador Hibrido - Gris Claro | D26: 92
C27: Simp Seal 25 Sellador Hibrido - Gris Europa | D27: 98
C28: Simp Seal 25 Sellador Hibrido - Café Obscuro | D28: 98 | F28: Gris Europa
C29: Simp High Tack Adhesivo Hibrido - Blanco | D29: 126 | F29: Blanco
C30: Acrilastic Sellador Acrílico - Blanco | D30: 46 | F30: Blanco, Negro
C31: Acrilastic Sellador Acrílico - Negro | D31: 46 | F31: Beige, Gris
C32: Acrilastic Sellador Acrílico - Beige | D32: 46
C33: Acrilastic Sellador Acrílico - Gris | D33: 46
C34: Backer Rod Cilíndrico - 1/4" Caja 1,219 ml | D34: 1680 | F34: 1/4" Caja con 1,219 mt.
C35: Backer Rod Cilíndrico - 3/8" Caja con 640 ml | D35: 1215 | F35: 3/8" Caja con 640 mt.
C36: Backer Rod Cilíndrico - 1/2" Caja con 762 ml | D36: 2050 | F36: 1/2" Caja con 762 mt.
C37: Backer Rod Cilíndrico - 3/4" Caja con 335 ml | D37: 1815 | F37: 3/4" Caja con 335 mt
C38: Backer Rod Cilíndrico - 1 " Caja con 182 ml | D38: 1732 | F38: 1 " Caja con 182mt.
C39: Backer Rod Plano Gris - 10 mm X 20 mm | D39: 4.1 | F39: Gris
C40: Cinta Norton Negro - 20 mts Ancho 1/4" X Espesor 1/8" | D40: 83 | E40: Ancho 1/4" X Espesor 1/8" | F40: Negro
C41: Cinta Norton Negro - 20 mts Ancho 3/8" X Espesor 1/8" | D41: 125 | E41: (Rollo c/20 mts.)
C42: Cinta Norton Negro - 20 mts Ancho 1/2" X Espesor 1/8" | D42: 166
C43: Cinta Norton Negro - 20 mts Ancho 3/4" X Espesor 1/8" | D43: 262 | E43: Ancho 3/8" X Espesor 1/8"
C44: Cinta Norton Negro - 15.25 mts Ancho 1/4" X Espesor 1/8" | D44: 102.5 | E44: Ancho 1/4" X Espesor 1/"4 | F44: Negro
C45: Cinta Norton Negro - 15.25 mts Ancho 3/8" X Espesor 1/8" | D45: 154 | E45: (Rollo c/15.25 mts.)
C46: Cinta Norton Negro - 15.25 mts Ancho 1/2" X Espesor 1/8" | D46: 205
C47: Cinta de Polietileno Doble Adhesivo | D47: 220 | E47: Ancho 12 mm X Espesor 1mm | F47: Blanco
C48: Cinta Selladucto | D48: 160 | E48: 48 X 50 mm | F48: Gris
C49: Masking Tape 3M - Beige | D49: 34 | E49: 18 X 50 mm | F49: Beige
C50: Masking Tape 3M - Azul | D50: 58 | E50: 18 X 50 mm | F50: Azul
C51: Festergrout | D51: 840 | E51: Saco con 30 kgs. | F51: Gris
C52: Gunther | D52: 110 | E52: Cartucho c/ 300 ml | F52: Amarillo
C53: Alcohol Isopropilico | D53: 60 | E53: Litro | F53: Incoloro
C54: Thinner | D54: 45 | E54: Litro | F54: Incoloro
C55: Placa de Neopreno | D55: 720 | E55: Mt2 | F55: Negro
C56: Placa de Neopreno | D56: 360 | E56: Mt2 | F56: Negro
C57: Trapo Limpio | D57: 44 | E57: Kilo | F57: Blanca
C58: Primer - Negro | D58: 2475 | E58: Litro | F58: Negro
C59: Primer - Gris | D59: 2475 | E59: (Cubeta de 19 Lts.) | F59: Gris
C60: Primer - Blanco | D60: 2475 | F60: Blanco

Sheet PED-60 CHAVEZ herrajes 00606 EM
A1: PROYECTO | B1: PEDIDO | C1: CLAN | D1: FAMILIA | E1: PROVEEDOR | F1: FECHA DE APROBACION | G1: LUGAR DE ENTREGA | H1: CONCEPTO | I1: SITUACIONES ESPECIALES | J1: IMPORTE
A2: =RESPALDO!F14 -> 00443 JAIME NUNO | B2: =RESPALDO!C13 -> 250 | C2: =RESPALDO!F15 -> MATERIALES | D2: =RESPALDO!C14 -> EM | E2: =RESPALDO!F4 -> JUAN ALEJANDRO CHAVEZ | F2: =RESPALDO!C42 -> 06/11/2025 | G2: =RESPALDO!F16 -> JAIME NUNO | H2: =RESPALDO!C15 -> EMPAQUES | I2: =RESPALDO!L40 -> - | J2: =RESPALDO!I43 -> 4872
